[{"fsize":102256,"hash":"Fii1v9jPazosiSPN5s9ep13eqMqd","key":"girl_b_img-0af450da48f71ce5b14d64e24974211f.jpg","mimeType":"image/jpeg","putTime":14456610110911547},{"fsize":236485,"hash":"FpSSX0FCbYmpaSusT4SeJSZwDo2M","key":"girl_b_img-0b83b35772cd51c2e0420911ca966e0d.jpg","mimeType":"image/jpeg","putTime":14456610131646558},{"fsize":334760,"hash":"FqXuHZYCm7YDBEX1TGy987uUBxgT","key":"girl_b_img-0bc4a906fecaf842a6a193dc84286776.jpg","mimeType":"image/jpeg","putTime":14456610150716438},{"fsize":24451,"hash":"FraNcxPg99vm4cK8lgPQNwVmYLkn","key":"girl_b_img-0c57fcd456e1d03a850cc2054ca04a35.jpg","mimeType":"image/jpeg","putTime":14456610153592078},{"fsize":71473,"hash":"FtWbYU8dSP8Hb8yGljy0RxQGNtZN","key":"girl_b_img-0c513db3c7108b4fd6de843484f2169d.jpg","mimeType":"image/jpeg","putTime":14456610158120924},{"fsize":49928,"hash":"FvvOBJDO8cnPugCJnMCGExhzeOLR","key":"girl_b_img-0d56fe3964e53a18683ad305e420ed4a.jpg","mimeType":"image/jpeg","putTime":14456610165863224},{"fsize":24565,"hash":"FvfHtuxE58voMdLnCAArfCz2gM7M","key":"girl_b_img-0dd18c3fb4cd46c743f289cecf3e284c.jpg","mimeType":"image/jpeg","putTime":14456610169146736},{"fsize":121014,"hash":"FixRMIL98ofw2pQ6VjQGlQug37rK","key":"girl_b_img-0e9c25638b9782afe0c5b6455fabc5c6.jpg","mimeType":"image/jpeg","putTime":14456610180640775},{"fsize":153517,"hash":"Fgx1bYyJqmdCIPyksOrUuWxcL14h","key":"girl_b_img-0e99f88fd74ed0f89b965db0c04e3a45.jpg","mimeType":"image/jpeg","putTime":14456610189523899},{"fsize":25972,"hash":"FlwKnrFwewxtKxOcb654luDCcX2l","key":"girl_b_img-0f7aecab4ac8010820089d8126485c66.jpg","mimeType":"image/jpeg","putTime":14456610194424715},{"fsize":114147,"hash":"FhHqPAWetrg3xk0hKdBIa6KAVW3t","key":"girl_b_img-001ab9d18668e2fb6a55e656a8106778.jpg","mimeType":"image/jpeg","putTime":14456610442598670},{"fsize":85818,"hash":"FtIPm7KrGTSjAArDLrH6wZpzMC2L","key":"girl_b_img-01e5c23365228e1cb2f56e894a70cdff.jpg","mimeType":"image/jpeg","putTime":14456610461647204},{"fsize":908430,"hash":"Fu0d9LoqvZxVUTdYFClYvRlc90NM","key":"girl_b_img-1ac7e795b9e29ec5c247c569d825b301.gif","mimeType":"image/gif","putTime":14456610553989302},{"fsize":111296,"hash":"Fie4c_F5i8sbg6e9ourmRmSCC-lU","key":"girl_b_img-1b2e5ec7d60c96675a792e7666fab15e.jpg","mimeType":"image/jpeg","putTime":14456610606472490},{"fsize":105339,"hash":"FsOAcngVpCLBf6RN9HRZRCs0m8Xy","key":"girl_b_img-1bc74440ff1dc875ef3a7df618629217.jpg","mimeType":"image/jpeg","putTime":14456610613991310},{"fsize":277937,"hash":"FrnWsHbdpnyrNjteFY70bTw6ZX6w","key":"girl_b_img-1c016290ff7baa6d4512f3c1bd340ee7.jpg","mimeType":"image/jpeg","putTime":14456610651149141},{"fsize":51467,"hash":"Fl82mUObcCmMGhTXMn-IeUjmS_pE","key":"girl_b_img-1c5266641649fbec0a411bd2f14e7f85.jpg","mimeType":"image/jpeg","putTime":14456610655433946},{"fsize":2471311,"hash":"FjBy0cohKFXqwfvNr0GbtjlSAMXd","key":"girl_b_img-1cae742607bdfa5c88a0e5c629c9513d.gif","mimeType":"image/gif","putTime":14456610880260145},{"fsize":51925,"hash":"FiXPoRfrEWf5sk2fBLTfijtRw-ZB","key":"girl_b_img-1cc8ece2703c52ae452812217eaac55d.jpg","mimeType":"image/jpeg","putTime":14456610885270943},{"fsize":256919,"hash":"FkKUpuwZKBUv3nNWTwYtcaUqHynK","key":"girl_b_img-1d831ab52767905a8ddb46f9716247aa.jpg","mimeType":"image/jpeg","putTime":14456610905764102},{"fsize":146711,"hash":"FsRp4Q1IaAxgIqlH800zY__frO6g","key":"girl_b_img-1d22917ae6bcf77be05d2d8959946b26.jpg","mimeType":"image/jpeg","putTime":14456610914601436},{"fsize":9500401,"hash":"ltNA1vnM6cJ6Hba61zR_bIqn-BDw","key":"girl_b_img-1e0d3bbe531cb91fbb1747c966f759c8.gif","mimeType":"image/gif","putTime":14456611867746869},{"fsize":1064548,"hash":"FgxoG944WznHqP0WdpXVFOkycQA4","key":"girl_b_img-1e2bb41dbc3daa12954f8e0aa4c694af.gif","mimeType":"image/gif","putTime":14456611985596693},{"fsize":71538,"hash":"FghYmkBZvcNYqH6IF_klPQkyl-ld","key":"girl_b_img-1e4c386afd31cd16cad6d474075294d8.jpg","mimeType":"image/jpeg","putTime":14456611996685656},{"fsize":53915,"hash":"Fp37BZgni0KN9gqEfoTDBDGVIGie","key":"girl_b_img-1e7f56f4841b907394660bd29fcd0187.jpg","mimeType":"image/jpeg","putTime":14456612003009273},{"fsize":64689,"hash":"Fn8UF8sgdYXnCdvN2lG45pgpqgbA","key":"girl_b_img-1e9bf55d4305dc822eff2c588153ced7.jpg","mimeType":"image/jpeg","putTime":14456612010859719},{"fsize":118970,"hash":"FvgML8nntGiyC2w9-_yCcUKNi0OI","key":"girl_b_img-1ee850d9b75fcb5c5f2a14c9ffc298d5.jpg","mimeType":"image/jpeg","putTime":14456612019135773},{"fsize":5025517,"hash":"lhV-UlJkHBc-sb7W_2rgLnV8cLG0","key":"girl_b_img-2a7aba2e6e5a3d8bf83509ec34ac5c1c.jpg","mimeType":"image/jpeg","putTime":14456612525196523},{"fsize":436133,"hash":"Fh21IHOiFxN0VTDQsbhkkd-lEO31","key":"girl_b_img-2b513d7b5e0cdd9a96abd4f0eaf4063b.jpg","mimeType":"image/jpeg","putTime":14456612584182526},{"fsize":39511,"hash":"Ftlf-Vublhw25pGezM_iMt3dup6H","key":"girl_b_img-2bb55cd8290fff60db418af537d6aa71.jpg","mimeType":"image/jpeg","putTime":14456612588223323},{"fsize":73390,"hash":"FoJfqn1VdTP4ArhNFSzd2vnj4QSd","key":"girl_b_img-2bde92d9c296d796898534d80dd7223b.jpg","mimeType":"image/jpeg","putTime":14456612593476906},{"fsize":66196,"hash":"FlNMDx1DhcGvXzxlTobp6XDrqNBk","key":"girl_b_img-2be78cf95df6ad764c31759e904cb30f.jpg","mimeType":"image/jpeg","putTime":14456612598950156},{"fsize":827370,"hash":"Fhjg3bA_FOUkQaL9oJsrQVEokVW5","key":"girl_b_img-2cff274676484eeb19b7664aa30ee546.jpg","mimeType":"image/jpeg","putTime":14456612640369392},{"fsize":926745,"hash":"FvFMooxgqT_2Uf-KXXtNF0rT7gWx","key":"girl_b_img-2dea41cec2c6ad213152d943ae110747.jpg","mimeType":"image/jpeg","putTime":14456612729945851},{"fsize":77915,"hash":"Fs7lqBFjhrLNth8zWE0CQH7ZjgNe","key":"girl_b_img-2f1baef68d090df647f21ef8c9bded39.jpg","mimeType":"image/jpeg","putTime":14456612741075461},{"fsize":234586,"hash":"FsFskwy_3xteQkfCUzFbvkh-eUgJ","key":"girl_b_img-2f1fd15c425dc38f5a86408a8095f2ee.jpg","mimeType":"image/jpeg","putTime":14456612754479427},{"fsize":43616,"hash":"FiT6F2VYYU5lpsaTmvMW8-QhTtLe","key":"girl_b_img-2f87846507393866ede246d9a5dd4214.jpg","mimeType":"image/jpeg","putTime":14456612759619305},{"fsize":143264,"hash":"FqwtGjpotWmziSxF1IYXnZIImiqB","key":"girl_b_img-3a64d1ed34d2a9dc292fc4d23ef0f25a.jpg","mimeType":"image/jpeg","putTime":14456612771178058},{"fsize":252948,"hash":"Fg_2mJ5L8Di2MBjpyhvyJQ3FTqN0","key":"girl_b_img-3ab054d158ca88bdebd0d67662d17f35.jpg","mimeType":"image/jpeg","putTime":14456612783343092},{"fsize":140198,"hash":"FgaQ20QTPyDLnbLkHKTGaiYRwDmG","key":"girl_b_img-3b4c1e729e405dd61e85748b83011821.jpg","mimeType":"image/jpeg","putTime":14456612794381413},{"fsize":114739,"hash":"FpY0hYIE-sNlPSvf5THGbkkk3-bh","key":"girl_b_img-3b38b901f41c4d010b5e76fb3e458dd0.jpg","mimeType":"image/jpeg","putTime":14456612809827173},{"fsize":191680,"hash":"Fs-MxcOmim5k1UsQioRj8mTIVdt7","key":"girl_b_img-3b60b668d80d90266534898b74e1d3e4.jpg","mimeType":"image/jpeg","putTime":14456612837692649},{"fsize":48881,"hash":"FkqcNa-NxiqCNkB5UhTfifkUdgl1","key":"girl_b_img-3b15552c0dfe05589e1360e0a0f0a01e.jpg","mimeType":"image/jpeg","putTime":14456612845222568},{"fsize":24886,"hash":"FkUQbvE_eAbY2L7SrKkV6qs60rAF","key":"girl_b_img-3b79323f34a50450117b997825efc41f.jpg","mimeType":"image/jpeg","putTime":14456612849014073},{"fsize":697763,"hash":"FjTlJv3PlZpNDsuucJwd0Bii_IfV","key":"girl_b_img-3be1e7e141ea534708846f144983983a.gif","mimeType":"image/gif","putTime":14456612926479838},{"fsize":85112,"hash":"Fn4CpHC2KjAmjP-Lz0X2xUjtfQ5U","key":"girl_b_img-3be10a8c082f08c7ca5b1f4b6fc11a4e.jpg","mimeType":"image/jpeg","putTime":14456612940973582},{"fsize":42112,"hash":"FkufXMB99mVNIf7mqB5mA3X2hgyg","key":"girl_b_img-3bedf300401015888631a16232c0af6a.jpg","mimeType":"image/jpeg","putTime":14456612946987511},{"fsize":540869,"hash":"FnlV4oMyfhCxvJnFzf1gGnUcFTAJ","key":"girl_b_img-3c6b6630d535f2c6f9d56ab5d3c4f5c0.jpg","mimeType":"image/jpeg","putTime":14456612993184700},{"fsize":206170,"hash":"Fhv1kqITVtr9_HyP-1__C_fUgedq","key":"girl_b_img-3c6e2589bc6bdc8fee011863c1defba6.jpg","mimeType":"image/jpeg","putTime":14456613005129747},{"fsize":551708,"hash":"FkdRzBPrHhzUE6d3Hv8xoOOAj3II","key":"girl_b_img-3c783854caef67b90591c7393c85f35b.gif","mimeType":"image/gif","putTime":14456613042689767},{"fsize":191901,"hash":"Fkt22oBqDOkDY2gRBd6d4B73bCUY","key":"girl_b_img-3cc19d3e057bde2b5409c582ba2b1be0.jpg","mimeType":"image/jpeg","putTime":14456613063787343},{"fsize":468885,"hash":"Fg5h9V-dccLACTn4tuuvvErKiJcb","key":"girl_b_img-3cd564ded2c9e06d8a6fe29448600442.jpg","mimeType":"image/jpeg","putTime":14456613093701602},{"fsize":67617,"hash":"FnNH3KPYZ1F59PAw2ZSoGS19IsM7","key":"girl_b_img-3cf3d11e827661fa7125bf6e705b125a.jpg","mimeType":"image/jpeg","putTime":14456613098261465},{"fsize":180140,"hash":"Fq7VwHwRc15XiAtHmT8dQYJbz_c8","key":"girl_b_img-3cf17a75c4b35ff65ffb6663048e5081.jpg","mimeType":"image/jpeg","putTime":14456613138360192},{"fsize":141941,"hash":"Fqci3KSo4fJsYKAbvETJb3S29m6k","key":"girl_b_img-3d11a3dc89901f88367276a6b2ab5391.jpg","mimeType":"image/jpeg","putTime":14456613158392769},{"fsize":53962,"hash":"FsjeJAfpmi-L3Lmh9NI3Y9QBJBav","key":"girl_b_img-3d64b98129d768ea9ec3cd2e5cf5d874.jpg","mimeType":"image/jpeg","putTime":14456613162730912},{"fsize":43573,"hash":"Flg3V2LxTnLJOjb9gXETMrWaezrU","key":"girl_b_img-3d202fd9d56a78f3671e585646244bf1.jpg","mimeType":"image/jpeg","putTime":14456613165717670},{"fsize":140071,"hash":"FpiihDF4JpzGbKpeGNy_gJf-Qxr7","key":"girl_b_img-3d1778fbbbafbf482ccadee58a65721b.jpg","mimeType":"image/jpeg","putTime":14456613173876254},{"fsize":117055,"hash":"FoxhrTddKn6Rw4iMLDw59KIvvWn1","key":"girl_b_img-3da2e4b19a15edcb1100706e12cf0245.jpg","mimeType":"image/jpeg","putTime":14456613191343622},{"fsize":2506592,"hash":"FlHUT4ZPg2_5oTeSEXD3444hI2os","key":"girl_b_img-3dfe7ae41d176db26d42e68a41ddcaff.jpg","mimeType":"image/jpeg","putTime":14456613440771115},{"fsize":107750,"hash":"FksShVqItt4xNmYL80lCXpUBDUky","key":"girl_b_img-3ea5cd19a18a435226172bcd9045e343.jpg","mimeType":"image/jpeg","putTime":14456613447901121},{"fsize":131020,"hash":"FskcxyBQJWJ7d-LtVCw70uC0otmt","key":"girl_b_img-3f2cc7bc18d067c32d6136f8d59afd3f.jpg","mimeType":"image/jpeg","putTime":14456613457027882},{"fsize":171537,"hash":"Ftsoxg7npjkLFwJ3JoqDWymysJoB","key":"girl_b_img-3f2d14fc937ecbe4479bd13c5d4fc9ac.jpg","mimeType":"image/jpeg","putTime":14456613467206599},{"fsize":698661,"hash":"Ft8F1F2-eJXdPk1ZV4Du9xVEIXm7","key":"girl_b_img-3fd122da08b210db4015a30a5b986a37.jpg","mimeType":"image/jpeg","putTime":14456613527409438},{"fsize":40241,"hash":"FjrlMIQXPoy2VqkNdf_NWRBTsBXh","key":"girl_b_img-3fe9aa6a6da8e3fe30a72a37b59aed47.jpg","mimeType":"image/jpeg","putTime":14456613531457217},{"fsize":3418783,"hash":"Fl2SDrZF8KQpg4LX6_Rpua_HrcP3","key":"girl_b_img-4a576e4eee6a66d4ac6f214d1aebe97a.jpg","mimeType":"image/jpeg","putTime":14456613741447445},{"fsize":62203,"hash":"FmUgmbYVbgfOHrlGdR4NXc94OLwM","key":"girl_b_img-4aebc0ed04173d24d17af620d4099b19.jpg","mimeType":"image/jpeg","putTime":14456613748197129},{"fsize":44181,"hash":"Fu4WSF_Z17vbgjYq-qADjbySMBI3","key":"girl_b_img-4b4e6189a92967903ac6ed8725fa95ad.jpg","mimeType":"image/jpeg","putTime":14456613752215589},{"fsize":186581,"hash":"FgUIcq4XDtDUJm1tIdq8T1X0Oj2c","key":"girl_b_img-4b7ae5d420569246d87aa93a33d1ae57.jpg","mimeType":"image/jpeg","putTime":14456613763388670},{"fsize":23536,"hash":"FiBlZgMR9xRl9KFdLZYMd09D60nx","key":"girl_b_img-4b98d4c449e52f2557cd837e0c0a1349.jpg","mimeType":"image/jpeg","putTime":14456613766308008},{"fsize":113053,"hash":"FnSkNKOhOi8iinGXY70dMkeNf865","key":"girl_b_img-4b5737119fbb092b2d9dee6f11781661.jpg","mimeType":"image/jpeg","putTime":14456613784704494},{"fsize":842487,"hash":"FqrCi7JbTuwHZYqCH9gQ9QVcvJRf","key":"girl_b_img-4c247e7d30f4b7cb14d4b2791dc7bcca.gif","mimeType":"image/gif","putTime":14456613850350541},{"fsize":113670,"hash":"Fh33WQPh3T7F53HC00vfAH7yVVjX","key":"girl_b_img-4cb8bcf8e56acbc52c578d85db994650.jpg","mimeType":"image/jpeg","putTime":14456613855834576},{"fsize":62483,"hash":"FtZfjjgMg7ivQBIngSdrU5KfQvF-","key":"girl_b_img-4cf06bf732fbfd1c98c18d0dbd406f90.jpg","mimeType":"image/jpeg","putTime":14456613860185780},{"fsize":113823,"hash":"Fu1YlGH1vfEdzmsmr9tE87BEBR1W","key":"girl_b_img-4cfd5667370528f6be9933f941c813a4.jpg","mimeType":"image/jpeg","putTime":14456613863895824},{"fsize":94280,"hash":"FumgyRZshGyFt1_aRya3GBUJZerg","key":"girl_b_img-4de886bdf43891e23b35ad4281e75914.jpg","mimeType":"image/jpeg","putTime":14456613868227576},{"fsize":460044,"hash":"FtkkmUqUOPFznB2VA9mkRFDcz66K","key":"girl_b_img-4e01ed041797b882a72dc8864e230009.jpg","mimeType":"image/jpeg","putTime":14456613896700635},{"fsize":118843,"hash":"FtSfUOvoIoEq54NHVrD5hQmZbDtW","key":"girl_b_img-4e8de652e13bd1b93eae15fdcfc37ddf.jpg","mimeType":"image/jpeg","putTime":14456613906515587},{"fsize":60011,"hash":"FjunFp2kSM7V6IPg9L6nl4Nh21gs","key":"girl_b_img-4e56842c72bc8521fb2881002bc1a4a7.jpg","mimeType":"image/jpeg","putTime":14456613912055838},{"fsize":109889,"hash":"FkjUn_GFMS2ouLvovECcBI5jTkf4","key":"girl_b_img-4ebf294b21c5d658236fd4a5eb287a67.jpg","mimeType":"image/jpeg","putTime":14456613917295930},{"fsize":151254,"hash":"FnWgkCJFfkcDRmrq-korqU1T5SUZ","key":"girl_b_img-4ee3c40f266abf4cc8df0cfe46322226.jpg","mimeType":"image/jpeg","putTime":14456613932184241},{"fsize":81330,"hash":"Fg3aOnxgsYtMAg6QKt1RO5haHZz2","key":"girl_b_img-4f68054d5181d1c8376af307cf3f063a.jpg","mimeType":"image/jpeg","putTime":14456613945689904},{"fsize":22485,"hash":"FpympwuzD0eZtcBGfdX4s0TUsDED","key":"girl_b_img-4f11963963b57ba17c1392b64c890e56.jpg","mimeType":"image/jpeg","putTime":14456613949546737},{"fsize":55689,"hash":"Fpwv8ySgF8Qqf_sSRmP0r-JFXIC8","key":"girl_b_img-05ff9a30822bbd211590a8146903363f.jpg","mimeType":"image/jpeg","putTime":14456613953732858},{"fsize":73820,"hash":"FmJ8jnagr2oKWCpEaLNEOzjXcSn8","key":"girl_b_img-5a8fcf6ae9a735d8e8ea2d6308157e04.jpg","mimeType":"image/jpeg","putTime":14456613958704611},{"fsize":176760,"hash":"FoSy3EgrSny0nxfS8dFTSJCcygrT","key":"girl_b_img-5b784b4e10071730f7575ba228113c4b.jpg","mimeType":"image/jpeg","putTime":14456613967756244},{"fsize":56571,"hash":"FtBjeEHIlHjGsOlPAi4gQVGLrmwi","key":"girl_b_img-5bec8d88d8114a28eff865514f002e8e.jpg","mimeType":"image/jpeg","putTime":14456613973417356},{"fsize":401784,"hash":"Fvg5RwdLYGAM_Eh9bn8z9gAEEAOS","key":"girl_b_img-5bffcfe77a0f2921d19aea0e06c753f3.jpg","mimeType":"image/jpeg","putTime":14456613994922934},{"fsize":83246,"hash":"FrV64NfKwEMpxLU8o-LUj4CvXCBY","key":"girl_b_img-5c9e0e9967cf3cc42a8165f02193db73.jpg","mimeType":"image/jpeg","putTime":14456614001421119},{"fsize":194091,"hash":"FvQJWIRaPlhTWf1Vt67KaWcK3SSr","key":"girl_b_img-5c85c8da5f414011b166fe452ef89d90.jpg","mimeType":"image/jpeg","putTime":14456614010407317},{"fsize":39940,"hash":"FqUFlMo5kCjr4dKb91bBeEkcLGXq","key":"girl_b_img-5cba5217716962b405338c106bae5c9e.jpg","mimeType":"image/jpeg","putTime":14456614014672885},{"fsize":99457,"hash":"FnXgnVCNeHXmkQn7dGRXWJ4vmzU2","key":"girl_b_img-5cde661f92a78b0817ab7676387425e2.jpg","mimeType":"image/jpeg","putTime":14456614023326891},{"fsize":97741,"hash":"Fj1pI5QGrgEAtTCRX03f3nZSokaJ","key":"girl_b_img-5ec132c5d15bb99590ffcbb486fb07b2.jpg","mimeType":"image/jpeg","putTime":14456614028869347},{"fsize":138836,"hash":"Fp3GW6PEfqAeptBhl2OVDWVy7qcg","key":"girl_b_img-5ee3f09653b783b5fd84703e381345de.jpg","mimeType":"image/jpeg","putTime":14456614034702460},{"fsize":82712,"hash":"Fosekr8Ks3ZsU2_2mdAppqos_c2J","key":"girl_b_img-5efacfac550edb5c2f3a411f9847c07c.jpg","mimeType":"image/jpeg","putTime":14456614040701743},{"fsize":46691,"hash":"FmVz91IUkTdkfSzUnG_4BwMHC7k0","key":"girl_b_img-5f7462636bb76ff2f2cc61342749b2bd.jpg","mimeType":"image/jpeg","putTime":14456614043842826},{"fsize":37307,"hash":"FgAcIVW4hQHxYh4rM3U1kgyW8CUt","key":"girl_b_img-5fbd6cfb8d2a924f2321ea00148710c7.jpg","mimeType":"image/jpeg","putTime":14456614046456326},{"fsize":696907,"hash":"FuAx1tcI5WOLSmUh1POWERdcvEC9","key":"girl_b_img-6a70b6209971dabeb4c6036ede555256.gif","mimeType":"image/gif","putTime":14456614072652396},{"fsize":41630,"hash":"FoacPYMDjhtanjJKd6ny2qUTmRfr","key":"girl_b_img-6a74f00dab0d0c4a5d39939414d618bb.jpg","mimeType":"image/jpeg","putTime":14456614075437252},{"fsize":64773,"hash":"FnidO2_QkJFzHFqmhBsV3Mp1ySd4","key":"girl_b_img-6b48c72a77f4ed781b472c8e64015e0e.jpg","mimeType":"image/jpeg","putTime":14456614080924354},{"fsize":278223,"hash":"FtesV3xMyxP_43SYO8GIMQnRFdhh","key":"girl_b_img-6b963b2792ce72d1ff76c6673c99e044.jpg","mimeType":"image/jpeg","putTime":14456614095640367},{"fsize":203732,"hash":"Fm0Oh3CT1ud24Wn7xTiq8qDW2fGQ","key":"girl_b_img-6ba6b8c01d5edf42bd87915cf40d10b4.jpg","mimeType":"image/jpeg","putTime":14456614102671154},{"fsize":52930,"hash":"FioN9aMMnMCQv5odWILMX1KDnw_7","key":"girl_b_img-6bcbe0e813a54224f2aee40a561319fe.jpg","mimeType":"image/jpeg","putTime":14456614106386681},{"fsize":92277,"hash":"Fk9Cct2Jh_NSbmY_YIpmymj6_WxC","key":"girl_b_img-6cf2bcf55a69ae9cf0bfc4e971a6c183.jpg","mimeType":"image/jpeg","putTime":14456614111661633},{"fsize":134591,"hash":"FvuCG_Ee0hAuVuWLLD7gkB2PzMFJ","key":"girl_b_img-6d2dce732ee3a0e8ded1fe34a18762cb.jpg","mimeType":"image/jpeg","putTime":14456614120282233},{"fsize":88298,"hash":"Fh9nwKztXmTG50Jlf-PxxF3nOdYA","key":"girl_b_img-6e8963b76668e8bcdbb97522b393e0a2.jpg","mimeType":"image/jpeg","putTime":14456614129939918},{"fsize":143761,"hash":"Fiijt2KOVcqoKEVR4-XAK8ZjdrvA","key":"girl_b_img-6e7541491bbe3bad140484ba126a07ac.jpg","mimeType":"image/jpeg","putTime":14456614142593545},{"fsize":166513,"hash":"Fs_tsbxso0Vz0pCfLMb2ITzWCCKh","key":"girl_b_img-6f4cb89d1673d55d5ffb69a8bde5aad5.jpg","mimeType":"image/jpeg","putTime":14456614156401593},{"fsize":94590,"hash":"FkeR2zZkIBLN09I6U0K4RfHNz5-C","key":"girl_b_img-6f8f0941954a5764e1fe1053e620c433.jpg","mimeType":"image/jpeg","putTime":14456614169040255},{"fsize":3902487,"hash":"FgNh3EBA6T-jgpnK8HwOgW01vQVD","key":"girl_b_img-6fd73fe49d9872f96e20ad417ad8b2d5.gif","mimeType":"image/gif","putTime":14456614324576120},{"fsize":88681,"hash":"FqEA0qef7sY9tBblmVp4EGUAxtD5","key":"girl_b_img-07fb2b42d74a458341800a1615ee8cac.jpg","mimeType":"image/jpeg","putTime":14456614331938341},{"fsize":93559,"hash":"FuHn3AP_xc9jrmjhNAChhfiye2Tr","key":"girl_b_img-7a8f81c273f69978c691f01c21f08f28.jpg","mimeType":"image/jpeg","putTime":14456614335365006},{"fsize":105031,"hash":"FgnO2cwiaC1qs2XCywBmU3JoqkAi","key":"girl_b_img-7ac5b2b517b068871e83c8e032260238.jpg","mimeType":"image/jpeg","putTime":14456614338640430},{"fsize":77882,"hash":"FsSe0HbPps8T42sal_mVZxG6pkGG","key":"girl_b_img-7ad31bc7d42de3da930b29d0243d86e1.jpg","mimeType":"image/jpeg","putTime":14456614342622659},{"fsize":95940,"hash":"Fu27jrPaU-ZVWaUBhoYpG15s5k31","key":"girl_b_img-7b65877dced88f37ab3df519f7925531.jpg","mimeType":"image/jpeg","putTime":14456614346686106},{"fsize":45476,"hash":"FkIsdqU0Hkq6pNtqLosGWLGG1Vd3","key":"girl_b_img-7bee89c36a5ed55dbeb9ce3be1a46183.jpg","mimeType":"image/jpeg","putTime":14456614354005582},{"fsize":99358,"hash":"FrctSmwHdspQEk7PqcSLGfQ1S-0V","key":"girl_b_img-7c2bc15d211eede3216a6ee4da6511fc.jpg","mimeType":"image/jpeg","putTime":14456614360152965},{"fsize":157772,"hash":"FgwvB6jpWekvUJL89XIfVTvOjk8V","key":"girl_b_img-7c43237b199226df6a83b27d92f1ae4d.jpg","mimeType":"image/jpeg","putTime":14456614365939984},{"fsize":1853148,"hash":"FoP23sQRiFlZXEHr2I1EQvXq7Z6g","key":"girl_b_img-7d29f2aece17d2c78b68c5f5c5d4cae5.gif","mimeType":"image/gif","putTime":14456614434569788},{"fsize":41465,"hash":"FgJXtcrCQoLOtHmuaHOhqK6p3LMW","key":"girl_b_img-7d559ee1161f9a8420e61e982b9d1a03.jpg","mimeType":"image/jpeg","putTime":14456614439154421},{"fsize":122507,"hash":"FgC5-ow6TyMGkp1B8j1v2QJAzHvu","key":"girl_b_img-7da14124ed94d5c891e67a49d39bc484.jpg","mimeType":"image/jpeg","putTime":14456614444129176},{"fsize":49814,"hash":"FrLkmPeFrOtQTS7vaBtLokqlasFJ","key":"girl_b_img-7ddde14db4496c38367b1546544e81f3.jpg","mimeType":"image/jpeg","putTime":14456614449598878},{"fsize":273499,"hash":"FuzvG0XiWf5Szeks8mDrtGXuvzPH","key":"girl_b_img-7e8265a44136410f114f577573d43361.jpg","mimeType":"image/jpeg","putTime":14456614459108550},{"fsize":428259,"hash":"Fi4FRFxvx5gIXfBnD69ertKKAPwE","key":"girl_b_img-7eadbf0367cbb720581abcdd2f32e070.jpg","mimeType":"image/jpeg","putTime":14456614472707842},{"fsize":54645,"hash":"FuL0vkjwN1Tj2SrcDJCvTQD3enRl","key":"girl_b_img-7ebfe81f29f78afb56277108dc1fa8df.jpg","mimeType":"image/jpeg","putTime":14456614476615688},{"fsize":25656,"hash":"FsxqVhgNExWhxDOUlzYr63QJIuzL","key":"girl_b_img-7ee0d5aa77eff3a06a3152a6616c6abd.jpg","mimeType":"image/jpeg","putTime":14456614478419918},{"fsize":222556,"hash":"FuKNd2tam7uwJ4Lp294cdo9-Jnpt","key":"girl_b_img-7ee5f518c1547b44e8a565fb5aa165d5.jpg","mimeType":"image/jpeg","putTime":14456614491720739},{"fsize":56862,"hash":"FlRChCjdhSAlVAauBI45N563cG4K","key":"girl_b_img-7eee9210e07ff1d113677f0d38030866.jpg","mimeType":"image/jpeg","putTime":14456614495214240},{"fsize":106046,"hash":"Fq-bRvq_Tx1heJJPIVgUuWlUnxp4","key":"girl_b_img-7faf90ea71f7bac96827f602d4b0f5f5.jpg","mimeType":"image/jpeg","putTime":14456614498755559},{"fsize":3333183,"hash":"FpQUHIxbMIAKa5Fpp7ftEyymj0Ma","key":"girl_b_img-08bf5c3009c9c27bc6ecfd0844741a06.gif","mimeType":"image/gif","putTime":14456614597495085},{"fsize":1086127,"hash":"FgkfWBJr0NDucE9WaCDnhIgEwe7y","key":"girl_b_img-08c1a365e89765736c1f474b90885729.gif","mimeType":"image/gif","putTime":14456614634486466},{"fsize":124235,"hash":"Frg9f0gEl1ZuwAJxGJ2YCM87NTMe","key":"girl_b_img-8a288af4344d5e8b119655ae4e55dc69.jpg","mimeType":"image/jpeg","putTime":14456614639851611},{"fsize":69711,"hash":"FhOlmoIBCQ7yOrmo3pMb7NM2MdyE","key":"girl_b_img-8aa800256a925cc1192c0f57645d52c9.jpg","mimeType":"image/jpeg","putTime":14456614643733446},{"fsize":1011144,"hash":"FlMpdJ-ELRsHryjx5-dreCE5VhVl","key":"girl_b_img-8b38f33fc63ffb33f06efc1a03d2cb4b.gif","mimeType":"image/gif","putTime":14456614671017191},{"fsize":29128,"hash":"FrJD0KA5PbGD8nxHdG55K4coDxD3","key":"girl_b_img-8b45560dce7674830f2fdb2d55d5e504.jpg","mimeType":"image/jpeg","putTime":14456614673113071},{"fsize":241781,"hash":"FulydTW9PtMwSkePmLGbcCgZhU2-","key":"girl_b_img-8be742304900269a48e7ddf60c5b5980.jpg","mimeType":"image/jpeg","putTime":14456614685862331},{"fsize":111901,"hash":"Fq-31N2ph1AfUqH3krNOKSScsiZz","key":"girl_b_img-8c4c8989666bed4cf48a3931fddbf40a.jpg","mimeType":"image/jpeg","putTime":14456614699526963},{"fsize":306210,"hash":"FiI7_HDE9fmW3f1EZkn4nkP5eWku","key":"girl_b_img-8c351be6318490311ca5fe1e18257db4.jpg","mimeType":"image/jpeg","putTime":14456614731440913},{"fsize":128443,"hash":"FunZgNbVDjWHWO-ttZ7ArqnxWoQ6","key":"girl_b_img-8d933eddbe2e221db0f44de576525754.jpg","mimeType":"image/jpeg","putTime":14456614739756692},{"fsize":123096,"hash":"FrlBi2VaicnAKSw4JjEu4N-TGlLl","key":"girl_b_img-8d81860db01d828b88976a6529e17ab2.jpg","mimeType":"image/jpeg","putTime":14456614747090222},{"fsize":113098,"hash":"FmGh8yNHkH8TzkY24xFkCIV0csQI","key":"girl_b_img-8ea990933c258749e35c8e32c5d89fa4.jpg","mimeType":"image/jpeg","putTime":14456614756153003},{"fsize":64288,"hash":"FtwD_NrLHLf3dQJ_y4xCgolXAxYJ","key":"girl_b_img-8ef5ab1b3e70afc32becb6beb1afd275.jpg","mimeType":"image/jpeg","putTime":14456614896225352},{"fsize":3902688,"hash":"FtkiD49GI1zJHf0nW-dCoZ1DgRFZ","key":"girl_b_img-8f72b5d2f79760eac2c76694c3dff1f3.jpg","mimeType":"image/jpeg","putTime":14456615050766970},{"fsize":5832862,"hash":"lgQawdv_GCK-HWOsBGI2VStVqe71","key":"girl_b_img-9a4f984b1c59c4735e95b8cf0534483a.gif","mimeType":"image/gif","putTime":14456615269484683},{"fsize":79830,"hash":"FqPH6Lf_XDoVWZ6cNp4e9g0rjY9a","key":"girl_b_img-9a8cce96bb7f2a1a5323645ed88eda14.jpg","mimeType":"image/jpeg","putTime":14456615274612243},{"fsize":69633,"hash":"FiTD7XoHku2FuhNq-PqnWg1Zu-v5","key":"girl_b_img-9a354f4c3008154eb920253946ec80f4.jpg","mimeType":"image/jpeg","putTime":14456615278062992},{"fsize":299018,"hash":"FqgpcXUzv9Ef3YmuPcIGZsgoHW2c","key":"girl_b_img-9aa0c09cbc995484b52c6ea5632853c8.jpg","mimeType":"image/jpeg","putTime":14456615289481316},{"fsize":806254,"hash":"Ft7Q06if0QvgqGr0eFlyqozPQi6G","key":"girl_b_img-9b54ba593a03ff3c47b56529ab596208.jpg","mimeType":"image/jpeg","putTime":14456615320340233},{"fsize":76884,"hash":"FkdcY1GLp1MwWyIYLTl-J8pVCAkB","key":"girl_b_img-9b54df6af04b4f5f85c2b6af073684c1.jpg","mimeType":"image/jpeg","putTime":14456615325586553},{"fsize":80577,"hash":"FuaoUrW6TMOanMSdK_LoqjlG-k4o","key":"girl_b_img-9b569c101e9c481de4b4a820d7d44655.jpg","mimeType":"image/jpeg","putTime":14456615330605278},{"fsize":159580,"hash":"FllyYO4nWaEzw4eqMcYYLTF6ADv6","key":"girl_b_img-9bb4ac093457a4d4335228c5645e4a15.jpg","mimeType":"image/jpeg","putTime":14456615338911735},{"fsize":106362,"hash":"FkEoE04pgtGqb-dRrapGDBR4b9Lv","key":"girl_b_img-9bc94b99d7d4fa80d41a26efc6fe94ab.jpg","mimeType":"image/jpeg","putTime":14456615343048344},{"fsize":33156,"hash":"FkKMfvIbcxuJxGAv_3UCd9genCIr","key":"girl_b_img-9bfa2fc1cbeb69f0e50b5e168282e3fc.jpg","mimeType":"image/jpeg","putTime":14456615345726999},{"fsize":247393,"hash":"FgYF-lxAOvIoC_xU_2I-0q0gNSVy","key":"girl_b_img-9c7d0d8ff06b59a2dfd8076fedbe8104.gif","mimeType":"image/gif","putTime":14456615355268596},{"fsize":101118,"hash":"FlD-OBIM8OlaXhQmZN_-z6xC5Ivb","key":"girl_b_img-9c25e35e3a994efd5266c5a1b35cc31f.jpg","mimeType":"image/jpeg","putTime":14456615360544979},{"fsize":33854,"hash":"FpUPwDxKzkk_nT3O9fLUAdWokcDT","key":"girl_b_img-9c69d42a35977a74a735994f2a376e86.jpg","mimeType":"image/jpeg","putTime":14456615363776712},{"fsize":176221,"hash":"FlWfXWMXTj390PhOyoihhS6svDiw","key":"girl_b_img-9dae6ef982f11f10687e97758fa46a5c.jpg","mimeType":"image/jpeg","putTime":14456615373283446},{"fsize":98144,"hash":"Fobpvo4tlqQvmk2vyXv3WWNxL3og","key":"girl_b_img-9e807ce9607df176179b1bb51a53182f.jpg","mimeType":"image/jpeg","putTime":14456615377970711},{"fsize":201392,"hash":"FgzTD6dKx8uC33iJhAWb1DYspfjS","key":"girl_b_img-9f068343dc1beffc129cf866258d7738.jpg","mimeType":"image/jpeg","putTime":14456615385441865},{"fsize":708438,"hash":"FhyKQMnxp96W-qWCdHUkdtCVyNLO","key":"girl_b_img-9febc2c1bbce144a460d4c6bf6fb2690.gif","mimeType":"image/gif","putTime":14456615429700617},{"fsize":66159,"hash":"FolQMge1NY3LoViBJzij9RGuHSra","key":"girl_b_img-10c149038ae1a8651528405053caaa0d.jpg","mimeType":"image/jpeg","putTime":14456615433066670},{"fsize":82970,"hash":"FiBs-Qs_x_pRt6Q0Anq-6Zu9x6U3","key":"girl_b_img-13c776b908588d03ada27ef203f762a0.jpg","mimeType":"image/jpeg","putTime":14456615438016126},{"fsize":41201,"hash":"Fsw9A4v9x1EdmR4vNh3uleVjQoTW","key":"girl_b_img-14dd8afaca8486546eaa217eb0e94b30.jpg","mimeType":"image/jpeg","putTime":14456615440673578},{"fsize":101846,"hash":"Fs86iqPeH3vzouFR6hitNjeSBVz8","key":"girl_b_img-15f9db056017a7bb6c1e55c1ce5e908c.jpg","mimeType":"image/jpeg","putTime":14456615446194325},{"fsize":122960,"hash":"FrIEERAxgibBaUyWjcrGlrC0rZDr","key":"girl_b_img-17cd2bb9a690646c1a53f48b7808a96b.jpg","mimeType":"image/jpeg","putTime":14456615450769536},{"fsize":862227,"hash":"FhxUTlQtuTytF6bcNY4NiwDfpL5_","key":"girl_b_img-17d1733477ebb217c55c10a1ada58e36.jpg","mimeType":"image/jpeg","putTime":14456615499609675},{"fsize":52979,"hash":"Fv2B0hPoElaWWgJoL7brGwk2wg4O","key":"girl_b_img-21b02bfe3b10db6417bf6876b89bec34.jpg","mimeType":"image/jpeg","putTime":14456615504630146},{"fsize":81681,"hash":"FgcyKeea0FbDcD_KoU_r-hBQc6_M","key":"girl_b_img-21d243b8cf2edf510b6c718a96e6d986.jpg","mimeType":"image/jpeg","putTime":14456615508169891},{"fsize":68932,"hash":"FgBu_h-dSV0nyEDYpkzZuId2k9ht","key":"girl_b_img-23a89a9e74a8b316a1c244491f2752c8.jpg","mimeType":"image/jpeg","putTime":14456615514528906},{"fsize":4095085,"hash":"FnSkpRkB7rrVsqCCJdkuUh9B_Sn0","key":"girl_b_img-23f1ed1ccf41f3558fef3b64ebbd7965.gif","mimeType":"image/gif","putTime":14456615682812995},{"fsize":71087,"hash":"FgZ7c8NSxD2pGSurHZdB-VLOWW42","key":"girl_b_img-26e4c08d919a8ef5840afd30c3ab93c4.jpg","mimeType":"image/jpeg","putTime":14456615687900730},{"fsize":228079,"hash":"FusZxdUH5l5Up1ObzMerNpJMfiFc","key":"girl_b_img-27b56463a231d7a231e23e78f81daa52.jpg","mimeType":"image/jpeg","putTime":14456615703057075},{"fsize":110309,"hash":"FsICqN5NDvPwYRq_7IIjCUvm494J","key":"girl_b_img-28f12a4c43bafe6d9d372d6d93850597.jpg","mimeType":"image/jpeg","putTime":14456615714868651},{"fsize":171310,"hash":"FpYYC2WMg7i_aLktBZkY5U7-rr_8","key":"girl_b_img-30b27852eff8fc03f0dfe3a72e84ac9c.jpg","mimeType":"image/jpeg","putTime":14456615726470426},{"fsize":3868273,"hash":"FvKzKkpBmAnZE9RH93c82ifEIbbv","key":"girl_b_img-30d5142a89141d78d6e98b70e43f2dcd.jpg","mimeType":"image/jpeg","putTime":14456615918683140},{"fsize":6240857,"hash":"lv57w4dX8sArN53sQQ1862GDhZWk","key":"girl_b_img-31a9b40f6aa944428e5e78a409f1ab1e.jpg","mimeType":"image/jpeg","putTime":14456616227925548},{"fsize":37169,"hash":"FqpbpPffMad96dLhtjdcJQeIc-9O","key":"girl_b_img-31d60d7ae2be488a6fdc00680603df98.jpg","mimeType":"image/jpeg","putTime":14456616230515070},{"fsize":24869,"hash":"FpFdc-cWyg2j2gEOSiRtOt7nRIH8","key":"girl_b_img-32ccfcdebcaa3e79b28670db3b6ed535.jpg","mimeType":"image/jpeg","putTime":14456616232481967},{"fsize":208229,"hash":"FgVouksIiDdqIeEjxZDPYaVbfyjD","key":"girl_b_img-34fd4f8187d8368d2edcf9758e065c9b.jpg","mimeType":"image/jpeg","putTime":14456616240598033},{"fsize":93919,"hash":"Ft3SPe-jGOBPbfzrZ2HC9wM2sRv5","key":"girl_b_img-38c7558eba95dfeed5404078fd45405b.jpg","mimeType":"image/jpeg","putTime":14456616246223703},{"fsize":109590,"hash":"FlMNVKpgl7VOMqg_J-50d2FBeiT4","key":"girl_b_img-39d316b1545c4ceb9718a7739e8fb14a.jpg","mimeType":"image/jpeg","putTime":14456616251346274},{"fsize":158161,"hash":"Fh3G_cLWBtyvylomYYvXuHCd177N","key":"girl_b_img-40d451e37701710ef643d111e67886b6.jpg","mimeType":"image/jpeg","putTime":14456616256740479},{"fsize":401971,"hash":"Fgde_H2LHRSrIiz3Gvs4dMqK5vEP","key":"girl_b_img-041ab71cae6607a5b48f6e53c66e8712.jpg","mimeType":"image/jpeg","putTime":14456616278784255},{"fsize":155522,"hash":"FsdqNEomt3Kxn5A7ThH_yGtVY_MW","key":"girl_b_img-41fcd3966f425143db8217d7819508c3.jpg","mimeType":"image/jpeg","putTime":14456616287461230},{"fsize":1619811,"hash":"Foh8iXzmfYeXt7vSSyBmrKIVkpDd","key":"girl_b_img-42e4e01570b8808efffef2d17da4b352.gif","mimeType":"image/gif","putTime":14456616388202972},{"fsize":121504,"hash":"FoIwGbTX6eMM9pkvq5vB38Vi7Yky","key":"girl_b_img-43a2f46b505d555f99de268e703e1990.jpg","mimeType":"image/jpeg","putTime":14456616394650809},{"fsize":251504,"hash":"FjmaFdzLhZpDmvn0xUVQg4Sw2Va1","key":"girl_b_img-44adf7d761cd9807ff9eb1de191b441d.jpg","mimeType":"image/jpeg","putTime":14456616407753002},{"fsize":103627,"hash":"FlE2ZdZ0ZHSip609sXbKHHFcvLNO","key":"girl_b_img-44c740fefefe17a26438313cfd554109.jpg","mimeType":"image/jpeg","putTime":14456616412245329},{"fsize":313226,"hash":"FqVUOcbyEZQfyp-PtaKZiHZ4PO0q","key":"girl_b_img-45a459bc3e7bc3f374c96b77df80d9c6.jpg","mimeType":"image/jpeg","putTime":14456616423853286},{"fsize":67944,"hash":"FsvYg1uWoA_j5a4wLkgjqrRmJ4Xh","key":"girl_b_img-47a4e972c72efbc49e6d6f4727ae317d.jpg","mimeType":"image/jpeg","putTime":14456616427090298},{"fsize":68986,"hash":"Fpgl_f6fzAgjAjEDvvrwKkFIgP47","key":"girl_b_img-48b8120f505284596da9846efcfaaf5b.jpg","mimeType":"image/jpeg","putTime":14456616430747553},{"fsize":71254,"hash":"FjeE_PKO3F45bdXfBM9L1Fwm19la","key":"girl_b_img-48e49edf30ed4dae9afef589778db9d8.jpg","mimeType":"image/jpeg","putTime":14456616434902665},{"fsize":227150,"hash":"Foou2GdhBW4xXOvjgbfzhqsNR1Vr","key":"girl_b_img-48fcf1af6038252482d96f2b87755386.jpg","mimeType":"image/jpeg","putTime":14456616442242884},{"fsize":389846,"hash":"Fsl70BZY_dfA4ywEFF1DxUAzkfIs","key":"girl_b_img-49bfdd6a50be3b80b5a59539f214df6e.jpg","mimeType":"image/jpeg","putTime":14456616454798362},{"fsize":165573,"hash":"FtEkFJ0k_xwBr533X7GTo2OuZ2La","key":"girl_b_img-50ad8e44a6233066833240b1725f3461.jpg","mimeType":"image/jpeg","putTime":14456616459847039},{"fsize":60007,"hash":"Fj2kefksTkHK9JMI7TV3nurY6v7H","key":"girl_b_img-50c8e1997ba6a4c5fda0b29cfddf3b4f.jpg","mimeType":"image/jpeg","putTime":14456616464073467},{"fsize":2008872,"hash":"Fm1uV1ePJgwH635Mclutidzg3I1f","key":"girl_b_img-50cf6f3192d1e4027cc1f51a0762962a.gif","mimeType":"image/gif","putTime":14456616525578726},{"fsize":242974,"hash":"Fkx23r13rDhgIRnkGB0L7QY2Btak","key":"girl_b_img-50de1a24fbcf7a13fd7a527ecaa3500f.jpg","mimeType":"image/jpeg","putTime":14456616535449058},{"fsize":837230,"hash":"FiuxqZ7Sh6oF0gI5yJ3EZayP52Nf","key":"girl_b_img-51e81721c0c05a4c7c09023d11f36c46.jpg","mimeType":"image/jpeg","putTime":14456616586604716},{"fsize":148359,"hash":"Fp0emV-9u3kYDAkJMux5UVcAWtfw","key":"girl_b_img-52a1312e1aa8b563d519cf38ee5fdab8.jpg","mimeType":"image/jpeg","putTime":14456616591181206},{"fsize":94384,"hash":"FmepY7v2IggeCmoDbedh46_j_QXG","key":"girl_b_img-053d079f31a17a6d45851bbbf4716887.jpg","mimeType":"image/jpeg","putTime":14456616598716035},{"fsize":460955,"hash":"FiTj85CAD11FwCUqKxvG-_xplsdi","key":"girl_b_img-53ac7b8c4df08b16854973de97c9bca9.jpg","mimeType":"image/jpeg","putTime":14456616623009101},{"fsize":56601,"hash":"FnAWMr_lET-YlrAZOMR9EBAUZppn","key":"girl_b_img-53d2177bee73488647a5617315883751.jpg","mimeType":"image/jpeg","putTime":14456616626212414},{"fsize":84970,"hash":"Fg9F9j-atZT2Y4q2-2zEOpZ5KreD","key":"girl_b_img-53eab17813f7a6fee4796758484eb34b.jpg","mimeType":"image/jpeg","putTime":14456616629973140},{"fsize":74464,"hash":"Fop9utJEgjEwOq7QVHPPbRvuFe0P","key":"girl_b_img-53f16556bffd60e7779a19544fa38598.jpg","mimeType":"image/jpeg","putTime":14456616633683011},{"fsize":411667,"hash":"FtB_Up4maPLhn5zuvJ_7OK2RJlEZ","key":"girl_b_img-55c079dda6a426d4df3982fd94209b4d.jpg","mimeType":"image/jpeg","putTime":14456616684960322},{"fsize":104492,"hash":"FncxSmy8oYiRvLSuqwDgTGzo-LbT","key":"girl_b_img-55c6872004e6e8fb05a9b9a7b3de0b47.jpg","mimeType":"image/jpeg","putTime":14456616690348697},{"fsize":53425,"hash":"FqnyvExAnspnIRS9dwOXWywTgCl_","key":"girl_b_img-55fa03b793f3ed5ebe7df3bc54a4ac50.jpg","mimeType":"image/jpeg","putTime":14456616694232785},{"fsize":215382,"hash":"Fo6D61_XU77my3xcvkd1yPEyEcT0","key":"girl_b_img-56cad7806c8ade90aa719cf4795176cb.jpg","mimeType":"image/jpeg","putTime":14456616710916794},{"fsize":92610,"hash":"Fob1Y4v6Q8tYFA3wqja3kq0XvOGq","key":"girl_b_img-56dd2c9c25b54da18a09f64f06f9c32a.jpg","mimeType":"image/jpeg","putTime":14456616721480235},{"fsize":78851,"hash":"FuPzxJpffrqZ7U9aj4zTvQ708osx","key":"girl_b_img-60aa8fa8b031f1027e73038d7152d78e.jpg","mimeType":"image/jpeg","putTime":14456616732486783},{"fsize":163133,"hash":"FsysKUbJjWBDaJ3y42ci5xM95QsT","key":"girl_b_img-60c0e20e27bfbeabee29526897c7cf56.jpg","mimeType":"image/jpeg","putTime":14456616748828750},{"fsize":39956,"hash":"FqEEukcwhQHa6XxUEwtJjiJNgkca","key":"girl_b_img-61f4b571733aa88cdd841ab335298389.jpg","mimeType":"image/jpeg","putTime":14456616752072714},{"fsize":80755,"hash":"Fnw2Htav7l3ENiTsufYXWPtT4Moq","key":"girl_b_img-64bc2d554343d8577cb88daf7be445b8.jpg","mimeType":"image/jpeg","putTime":14456616761288682},{"fsize":104048,"hash":"FqeVdEtPv3g0hqNBNOaMlyb0hA-3","key":"girl_b_img-64c9ad8f0efb1cd147d4b62ac7789df9.jpg","mimeType":"image/jpeg","putTime":14456616767965680},{"fsize":82441,"hash":"Fjc6olgSExC_CVyEyihj1aDVzljd","key":"girl_b_img-64f0e228b294e4b0c2ef0691b83ab33c.jpg","mimeType":"image/jpeg","putTime":14456616777010624},{"fsize":335409,"hash":"FmKhUZOVGbuRxxOFYkUlc2esTB3Y","key":"girl_b_img-67b7e56bec87763bef7d033f56485c8c.jpg","mimeType":"image/jpeg","putTime":14456616807932932},{"fsize":42504,"hash":"FhXjv_mNFICvXwhVNFfnhgqrUNTQ","key":"girl_b_img-67bc53c81bc834d719e71bbdc3dbe4cd.jpg","mimeType":"image/jpeg","putTime":14456616816648551},{"fsize":105368,"hash":"FhCc7zXjthwL8QX07FQnOtQaS3Uw","key":"girl_b_img-67c5a6412f61ef0b55d0d3508574fc13.jpg","mimeType":"image/jpeg","putTime":14456616824320971},{"fsize":41657,"hash":"Fq4rjEUiY2WgT_F2w3IiFMYGyrJd","key":"girl_b_img-67d4c4f77b82c33af822aca951a9d872.jpg","mimeType":"image/jpeg","putTime":14456616827404882},{"fsize":339569,"hash":"FtLaMpbhlQWP9LhKtFEWWZiJ9D96","key":"girl_b_img-68a4f07fd7dba47affb838576bed86bf.jpg","mimeType":"image/jpeg","putTime":14456616870644912},{"fsize":144820,"hash":"FvE1sVSoPpA1WEEdi-QNlLvpvXxL","key":"girl_b_img-68effc425a2c566dc7da799d8bb2b0bb.jpg","mimeType":"image/jpeg","putTime":14456616891691720},{"fsize":221566,"hash":"FuTASDXxeUHpGQ7MuFScsMegPsJD","key":"girl_b_img-69f3ad7a66c3f3aca6e6dae3ab8bbb86.jpg","mimeType":"image/jpeg","putTime":14456616924020864},{"fsize":75653,"hash":"FmTAW8GJ9FavBCc8N2Z3FwbNwT9I","key":"girl_b_img-69f8aa9145596ca5898695000ad73520.jpg","mimeType":"image/jpeg","putTime":14456616931150262},{"fsize":171158,"hash":"FvtLXxVzdTfQzvy_QymgBUYlrsFo","key":"girl_b_img-70c6d854fa910c4de14c7003b87e7828.jpg","mimeType":"image/jpeg","putTime":14456616948849711},{"fsize":112141,"hash":"FocXfL1E6pSfyXyadDAXDS3QDg6F","key":"girl_b_img-70ea364a56bd3551b68f5c888b31a429.jpg","mimeType":"image/jpeg","putTime":14456616957648948},{"fsize":2637873,"hash":"FsbXAOm36rffsB7Au7Y0kWTjvmLt","key":"girl_b_img-71a9fb5b238412ea411e8ea2885968ff.gif","mimeType":"image/gif","putTime":14456617143717324},{"fsize":419018,"hash":"Fhz0AzA5-8yTGyrHQKLBj6aJmNOZ","key":"girl_b_img-71dc41a435f2511b11f15b56bccddef4.jpg","mimeType":"image/jpeg","putTime":14456617175864067},{"fsize":85672,"hash":"FvIoPvOkaaQxL7-Bk56kUtUOpJwn","key":"girl_b_img-71f99eeee3d45fa7747cb9f77c125bf2.jpg","mimeType":"image/jpeg","putTime":14456617191432672},{"fsize":700790,"hash":"FpmY9nOsbOTFIrvG3N2F2hT3wgi4","key":"girl_b_img-074c032ad66c01c89a677c8e49a5765e.jpg","mimeType":"image/jpeg","putTime":14456617251512897},{"fsize":64867,"hash":"Fv3d5HxiugGEw8F0OULP-1KmC2zy","key":"girl_b_img-74b50f7d0adcd12c3d81488ec6a7d451.jpg","mimeType":"image/jpeg","putTime":14456617258611000},{"fsize":221943,"hash":"FtnP1HlZNLSLwOAfOvaP0QwOWyo6","key":"girl_b_img-74d7258220d60a56a317f45ee64ad4c5.jpg","mimeType":"image/jpeg","putTime":14456617275152248},{"fsize":153203,"hash":"FtJsyBiCHqhs_PsmQOZk5JY361NK","key":"girl_b_img-78c3c6ac21b024f8b8fd76ff204edde6.jpg","mimeType":"image/jpeg","putTime":14456617288786103},{"fsize":153471,"hash":"FsOPL4ScekBwIYnZrczfpvqr6sac","key":"girl_b_img-78f3865af1a4cbc120a40a479fea8fa7.jpg","mimeType":"image/jpeg","putTime":14456617308402480},{"fsize":134872,"hash":"FuzTaK2S2jeQmYrne2fxzXyxz0CG","key":"girl_b_img-80cdf9e671e9adc509cfc0d012a935e0.jpg","mimeType":"image/jpeg","putTime":14456617317927797},{"fsize":2720010,"hash":"FsXS9DTgpYVSpseGyVnIyuGJt4Fn","key":"girl_b_img-81be6163e415901c640a55adf6d88350.jpg","mimeType":"image/jpeg","putTime":14456617530511735},{"fsize":141435,"hash":"Fg97zAOTAjb0Fs-fgtLsHTzGyf24","key":"girl_b_img-83a5928cc546981b8686e794ee06d77c.jpg","mimeType":"image/jpeg","putTime":14456617540039849},{"fsize":100209,"hash":"FgS_Mr8zws7ig6aADW9N8aGhU8Z_","key":"girl_b_img-83ab916cbdb68d9566369641d75e6f01.jpg","mimeType":"image/jpeg","putTime":14456617552552027},{"fsize":114439,"hash":"FudiW-rSVRTdFII40zNjuz16JLKh","key":"girl_b_img-85d06227d1ca93574f303bc10836f306.jpg","mimeType":"image/jpeg","putTime":14456617570244042},{"fsize":140748,"hash":"Fk-HI5Ao9QnAWrSak6dLkUWguiKO","key":"girl_b_img-87b1ee726f32dff3f4b88d6d1b8e3056.jpg","mimeType":"image/jpeg","putTime":14456617578145053},{"fsize":173810,"hash":"FppZXRMFEuThRNdAV_Kx7_pRT2r9","key":"girl_b_img-87c64c7e53734e0aab06e944aecc95dc.jpg","mimeType":"image/jpeg","putTime":14456617589400227},{"fsize":140665,"hash":"Fu4_OluFg-NXZFp-NHF61ttRZ49y","key":"girl_b_img-87dfb02c54fe8d3c27bc7d40eda09190.jpg","mimeType":"image/jpeg","putTime":14456617596712040},{"fsize":2087789,"hash":"Fh1xSGO3JPuITE3xqkmtzbWC9vrO","key":"girl_b_img-87e13525e1b5a83e933ba55691722c33.gif","mimeType":"image/gif","putTime":14456617786246600},{"fsize":113757,"hash":"Fn39JDMGB5C7HDHbsJYkok0MTvOk","key":"girl_b_img-87e85125fc8f1bd86cf4fb27cade66a6.jpg","mimeType":"image/jpeg","putTime":14456617799754653},{"fsize":424634,"hash":"FlO12Mju5rh6vUNuyaRaKj7ueDQv","key":"girl_b_img-88acc72508b4ca36606eb5f82a473254.jpg","mimeType":"image/jpeg","putTime":14456617845997653},{"fsize":135953,"hash":"FvSmmYJfSKgMuPod5ohqW8CN9nBs","key":"girl_b_img-89ca2f44d51c6cf2ca7acc0ddd9e5a08.jpg","mimeType":"image/jpeg","putTime":14456617861159310},{"fsize":98666,"hash":"FiLITPRqiSDovmuK7_SlhoF0tXQE","key":"girl_b_img-91b9f75b6f053db85252da6cd63fd17b.jpg","mimeType":"image/jpeg","putTime":14456617867556547},{"fsize":216197,"hash":"FlpKmaLN2voYPET3ewKoN2xAKHK0","key":"girl_b_img-92a525ba937df73f22c66c36e3333928.jpg","mimeType":"image/jpeg","putTime":14456617886516557},{"fsize":111769,"hash":"Fi_PAv2WpckkQ0PAByv4Wnm0QUC9","key":"girl_b_img-93f08fb7724302a92e9c44aa4d4625e0.jpg","mimeType":"image/jpeg","putTime":14456617911942801},{"fsize":418104,"hash":"FiSsCbkAGHDM8T5zu25NPfqDFwds","key":"girl_b_img-98ba205200198990b5205d40d0ce9d5e.jpg","mimeType":"image/jpeg","putTime":14456617957989576},{"fsize":72462,"hash":"FlvVh6o9U2unHsNFlQ7qDhlhl9Qt","key":"girl_b_img-99e1da4a8909963f104c6d2482cd1b96.jpg","mimeType":"image/jpeg","putTime":14456617968223594},{"fsize":55367,"hash":"Fp3BUUObl6aCT0hws0Jc-74iB7iq","key":"girl_b_img-104d7a3fa462e9cab3df4eb46bb9a184.jpg","mimeType":"image/jpeg","putTime":14456617972729131},{"fsize":61341,"hash":"FpRSGElO0wYs48rDm05QO7Htt_10","key":"girl_b_img-123f3a07326bce63547eec18d682837d.jpg","mimeType":"image/jpeg","putTime":14456617976625525},{"fsize":208498,"hash":"FkhM-nkmwxfdWq-3x0cZ58rjLekb","key":"girl_b_img-189a513c1ff3174c12e8e7da6ce8f504.jpg","mimeType":"image/jpeg","putTime":14456617991784604},{"fsize":134728,"hash":"Fm6hniBm-M0b-xsVRIIMLXTgmQg-","key":"girl_b_img-200b751d4105eee143353d9a92391854.jpg","mimeType":"image/jpeg","putTime":14456618008912473},{"fsize":41622,"hash":"Ftyxxy1UyXDb7vaTMTjRlvUl-XcZ","key":"girl_b_img-208e655600a984e9bae6346e5b6f7d4d.jpg","mimeType":"image/jpeg","putTime":14456618014286617},{"fsize":225587,"hash":"FsQhAyFKfOkqpNf55f9qqfk5230n","key":"girl_b_img-222a8270ff27a713cc2ad173a331c217.jpg","mimeType":"image/jpeg","putTime":14456618026062863},{"fsize":82787,"hash":"Fpi6uPe0vptIP9yaPEz-MBJ3XKV_","key":"girl_b_img-231d27aa708890b6519dfdf6394c9eeb.jpg","mimeType":"image/jpeg","putTime":14456618036212975},{"fsize":104738,"hash":"FoFrH7Ako4SDyj-xqcEVDkr8HU5Y","key":"girl_b_img-258a34822d2c18f01e669954080a1c34.jpg","mimeType":"image/jpeg","putTime":14456618049846552},{"fsize":92098,"hash":"FiUcqAT-OkJiw4IVupbj6Gr8Xu6O","key":"girl_b_img-270ac08ef62fa49b49852afce4097d1f.jpg","mimeType":"image/jpeg","putTime":14456618055276835},{"fsize":195406,"hash":"Fvoi9m6wU0tRJTpoHXwb08KQAKub","key":"girl_b_img-270fdbfb238e5d121d09537d1daa4bd7.jpg","mimeType":"image/jpeg","putTime":14456618075457245},{"fsize":3924788,"hash":"FjkafyaH_pacLP3g1dzMzF7hnnJ_","key":"girl_b_img-279a8d69d9437b7949c1260cba86c10d.jpg","mimeType":"image/jpeg","putTime":14456618395655610},{"fsize":179884,"hash":"Fvtmq8MzqgT50AsLFUNDZLpNeC-G","key":"girl_b_img-355cd336278eedf5126a85770f005674.jpg","mimeType":"image/jpeg","putTime":14456618409542339},{"fsize":513796,"hash":"Fk9Z12kn3nH6_KGj2Z6-hBkgv_k-","key":"girl_b_img-412d280c34f2594112cb8e8fd28b65a6.jpg","mimeType":"image/jpeg","putTime":14456618434212506},{"fsize":2262401,"hash":"FlsOC9-0VNXxZLcVWujEaRlLSnd1","key":"girl_b_img-417ecb6608cc47ef6427d63f780e19c8.gif","mimeType":"image/gif","putTime":14456618589056751},{"fsize":2539360,"hash":"FnrrtyXG8bko-fZqELO26VR2VRV2","key":"girl_b_img-426f3cb14a50f3e70f16c64635f8b759.gif","mimeType":"image/gif","putTime":14456618780834576},{"fsize":197473,"hash":"Fgq3vdIXmHAKM9MlfouOIATrVo6L","key":"girl_b_img-430eb7038ac2bb603ddd536a893f47c7.jpg","mimeType":"image/jpeg","putTime":14456618797655273},{"fsize":215074,"hash":"FjFsQCfUFW--6Lq8upXNHT5mwNi3","key":"girl_b_img-490d0f6112c330a2b89a1a8c72bdbb04.jpg","mimeType":"image/jpeg","putTime":14456618809607125},{"fsize":167112,"hash":"FvG0TEx0OexlPjBPZ726qQa0puHt","key":"girl_b_img-500dee39caad1da95a6bfbf07747063a.jpg","mimeType":"image/jpeg","putTime":14456618823163046},{"fsize":129325,"hash":"FgUT3GvGuuma1gdymv5yU5Bplk3L","key":"girl_b_img-530f59c011fe6607c683eb3449578e38.jpg","mimeType":"image/jpeg","putTime":14456618836315214},{"fsize":560115,"hash":"FnvPA1W7Q97Cd7mtQzRHr8heqHUM","key":"girl_b_img-545ea50bc793ee783b050dc65d4e048a.jpg","mimeType":"image/jpeg","putTime":14456618871241760},{"fsize":61341,"hash":"FpRSGElO0wYs48rDm05QO7Htt_10","key":"girl_b_img-551afdcefef82f43d81feb3a513dabe3.jpg","mimeType":"image/jpeg","putTime":14456618875415240},{"fsize":112147,"hash":"Fhsmse9rWb8HT3jyxrvhlPTYrQ3j","key":"girl_b_img-597db02c4424fea1033d596c3ae77180.jpg","mimeType":"image/jpeg","putTime":14456618885362223},{"fsize":189695,"hash":"FoWIdM5nOhsqSGvKq2IdpM8nf-Iu","key":"girl_b_img-602b046785ca1efd602a56e17ea6d0be.jpg","mimeType":"image/jpeg","putTime":14456618901907695},{"fsize":127811,"hash":"FpZQ_yHTCdPfsEOT9rr-2e3AgjyI","key":"girl_b_img-631bc00738e0700fa9e62c29537280f3.jpg","mimeType":"image/jpeg","putTime":14456618920866859},{"fsize":23964,"hash":"Fh2bCp1xhPScJb1tlGQncFXpgxyY","key":"girl_b_img-634e065cf4beaaaffc11b93f8b7dcd35.jpg","mimeType":"image/jpeg","putTime":14456618926660787},{"fsize":41929,"hash":"FmgvJ-O9j0UlzUqGjGzir-ja2bal","key":"girl_b_img-635c220600d0582770450a3dca76f1df.jpg","mimeType":"image/jpeg","putTime":14456618931077681},{"fsize":2063296,"hash":"FqCejFhflGXyJeHTo-IiCqWTl7Uo","key":"girl_b_img-659e3f09d2bb681b53e896833fd36b02.gif","mimeType":"image/gif","putTime":14456619070083812},{"fsize":69149,"hash":"FpxvG_gPMFsKb8jKerJovXLQ0zvX","key":"girl_b_img-667c2ae7f3411c6a5fedd611d91998b2.jpg","mimeType":"image/jpeg","putTime":14456619077121342},{"fsize":4763127,"hash":"lpnRqcrPax6snySXuTkqHxGkWfK6","key":"girl_b_img-678ea4ac8d61447755a4d47e17c49a57.jpg","mimeType":"image/jpeg","putTime":14456619462234447},{"fsize":186454,"hash":"FnVQVsGahFOjizVorNYNztE0k-17","key":"girl_b_img-0726a50a40ad6fde87ed7b94c0884a15.jpg","mimeType":"image/jpeg","putTime":14456619475931822},{"fsize":2743450,"hash":"FoAoncMBLW0CE5PsnayCndxppIG3","key":"girl_b_img-742f76dace4bb00545a23f342e51b791.jpg","mimeType":"image/jpeg","putTime":14456619690157424},{"fsize":45526,"hash":"Fi42X_HpLwJEQL1QQKp8ajtHrdBy","key":"girl_b_img-754e93a307964f34127757b94577ba43.jpg","mimeType":"image/jpeg","putTime":14456619695960148},{"fsize":384683,"hash":"Fqxd5yD692QzWyCsU_mQ35VtUozc","key":"girl_b_img-756f559b2598a37cbf2d158b1f9cf7bf.jpg","mimeType":"image/jpeg","putTime":14456619724852329},{"fsize":333708,"hash":"FnS6Mr8x4V24Ybp6GjVHVpyPeJ7p","key":"girl_b_img-779d10aaf42b4b9e784bf4827ec66d48.jpg","mimeType":"image/jpeg","putTime":14456619739950231},{"fsize":79757,"hash":"Fikrk5JFURIz_lEQnMTLYKC4aibq","key":"girl_b_img-780b41eeba5e8037529efc435adf2938.jpg","mimeType":"image/jpeg","putTime":14456619752469241},{"fsize":43198,"hash":"FlCyqoJB8SOMtFY_aVPPSVoU21L_","key":"girl_b_img-809af4aa3b7602615ddbad2158ca0ce8.jpg","mimeType":"image/jpeg","putTime":14456619755686754},{"fsize":50424,"hash":"FuaW8v0543vUPy1-MHasuWil-zny","key":"girl_b_img-854a04dda586ec915435e6f320bc4ff2.jpg","mimeType":"image/jpeg","putTime":14456619763849904},{"fsize":85647,"hash":"Fq3RM08VRNhN7lRbCpuW3ES1jqPk","key":"girl_b_img-874b0070b41a81b4f7ea89f179f207f2.jpg","mimeType":"image/jpeg","putTime":14456619771009036},{"fsize":144925,"hash":"FgeWa7rmR0zEK64JWguBEsRGNWGp","key":"girl_b_img-877f440638da1edefe9dd89267979496.jpg","mimeType":"image/jpeg","putTime":14456619778207177},{"fsize":3140729,"hash":"FkDsHCDpvGVzK9UGp0upS8MXS4mR","key":"girl_b_img-887e89742ec731bb41a8699920d0b2f7.gif","mimeType":"image/gif","putTime":14456619965012692},{"fsize":2066478,"hash":"Fh8ojoZOrrr1Fw0dBOlFtohTEktb","key":"girl_b_img-897fea444df1eb489dbc517149c561e7.gif","mimeType":"image/gif","putTime":14456620072050094},{"fsize":147010,"hash":"FpISQBXw9qcZxTsge6nZhyzcp3jB","key":"girl_b_img-986fc75bffbfe54d8ab9b22efca6e9d9.jpg","mimeType":"image/jpeg","putTime":14456620080652309},{"fsize":83780,"hash":"FpSfEcDNMXLND06v8TR7f-FDUp_c","key":"girl_b_img-989da07ab47deb5bc77a1b281632f93a.jpg","mimeType":"image/jpeg","putTime":14456620088377298},{"fsize":231516,"hash":"FjMwL_kvWHYTXSjvb92d0R8ouXgU","key":"girl_b_img-1139f90032fc29e064fd1768f7911e8a.jpg","mimeType":"image/jpeg","putTime":14456620098719086},{"fsize":70773,"hash":"Fmt7UdZe_rFS4s4tO153WtEsyMlX","key":"girl_b_img-1227b076f3eaef9ed27fd3ff634ded47.jpg","mimeType":"image/jpeg","putTime":14456620104950907},{"fsize":2217905,"hash":"Fr7R9vc0txHlW71St_0yuIypTBXp","key":"girl_b_img-1745cfd70ba3f66994ee3cb0dba48d3f.jpg","mimeType":"image/jpeg","putTime":14456620265759871},{"fsize":1397751,"hash":"Fv2C_WhaTGDUMn-YHcYkdakvBIlW","key":"girl_b_img-1875f9a3daa9c8a83ac48b8dfb168118.gif","mimeType":"image/gif","putTime":14456620351968576},{"fsize":169084,"hash":"FtgJTWtiV9AFANh6B7Kb-SP1cArF","key":"girl_b_img-1885aef4d6abd29a73a365dc556ab70b.jpg","mimeType":"image/jpeg","putTime":14456620358787838},{"fsize":32572,"hash":"FvtyrW69aoJrBQy6ms58YqKkfH32","key":"girl_b_img-02478e4d8feb7affa38a1cf8df3f04f8.jpg","mimeType":"image/jpeg","putTime":14456620361908363},{"fsize":71432,"hash":"FjA1bmA3qj51u5jg6lp9yl6OsWeg","key":"girl_b_img-2581ef0136e5d24191362e972b32647a.jpg","mimeType":"image/jpeg","putTime":14456620369564744},{"fsize":131402,"hash":"Fi90cI42UmIc1hcHVMe4qV8bXel-","key":"girl_b_img-3736cf75474999349db360def7466afa.jpg","mimeType":"image/jpeg","putTime":14456620376963429},{"fsize":46987,"hash":"FnV-LJe4-Os8NRNL-THKZ4ZIGtuK","key":"girl_b_img-3756da1a1bacdb95c4b326f6a544713f.jpg","mimeType":"image/jpeg","putTime":14456620380232363},{"fsize":52417,"hash":"FjaOxc0B9ojAWjqHqGoHGr-og42q","key":"girl_b_img-3913ac735a47ec69bf01adaaeaad96cd.jpg","mimeType":"image/jpeg","putTime":14456620385492321},{"fsize":137240,"hash":"Fnqsf_759x_hM3tp__Rejs4XVxow","key":"girl_b_img-4168f00216f7c4bbd330f5b37e9c2d5d.jpg","mimeType":"image/jpeg","putTime":14456620395622518},{"fsize":124356,"hash":"FsJOmmxT62Tx8_dHO232lBWmLL6_","key":"girl_b_img-4442cef6f71d62981f134e54ba934cb7.jpg","mimeType":"image/jpeg","putTime":14456620404366685},{"fsize":131064,"hash":"Fqpr0qh7QZwa4WuT6E8koCTkexA_","key":"girl_b_img-4615cb45f6c4b2fc3c0c50b908fc8d3e.jpg","mimeType":"image/jpeg","putTime":14456620410984267},{"fsize":23711,"hash":"Fv7GmFJF-pHqzng_7THC89tK5NcS","key":"girl_b_img-5217bd6a40a4b9131f6c260b31f2ebb7.jpg","mimeType":"image/jpeg","putTime":14456620413854932},{"fsize":107635,"hash":"Frj2SkneI9RKkbpQLnCXO77JykFO","key":"girl_b_img-5584edbc5d16b1e1fa300398a60511e3.jpg","mimeType":"image/jpeg","putTime":14456620425740401},{"fsize":107578,"hash":"FpgRoTZp2co-ue3tYM4EBbIdLbrb","key":"girl_b_img-5785f65b33e8d23b0c7813113dba2d9b.jpg","mimeType":"image/jpeg","putTime":14456620438427613},{"fsize":227168,"hash":"FmH7chfsgPFBAKxGV5wCKqzxz7i2","key":"girl_b_img-5882a46bb681256e9e06172927e09201.jpg","mimeType":"image/jpeg","putTime":14456620451107312},{"fsize":2148269,"hash":"FqmJPv12Nwdbs_kSQrXQItALKrGK","key":"girl_b_img-6449c4352a7f077a58c420a2811118e6.gif","mimeType":"image/gif","putTime":14456620595067009},{"fsize":139044,"hash":"FnjlvrT8HGeSzF13YzGDrkVJ0hcD","key":"girl_b_img-6564cbf80ff51691271ba88f1e28a879.jpg","mimeType":"image/jpeg","putTime":14456620612625514},{"fsize":152855,"hash":"Fn94RpYZRBjfQu5g6nfnopj4KUp-","key":"girl_b_img-6624ba62422f52eaba2db04c90a2d9c3.jpg","mimeType":"image/jpeg","putTime":14456620628669646},{"fsize":52822,"hash":"FqEq73zF3m19LEnPw3rI0bLjrhyk","key":"girl_b_img-7447a67766b2a003a400806f0d7b9df2.jpg","mimeType":"image/jpeg","putTime":14456620635247451},{"fsize":71044,"hash":"FpwrsHwQKggPNqep5kBySxZZIPpN","key":"girl_b_img-7576a0ce9e53dca798c3a84c843501b9.jpg","mimeType":"image/jpeg","putTime":14456620646626201},{"fsize":528751,"hash":"Flt2YoFDpVb8YApwC8vYmRQQa5Nk","key":"girl_b_img-7801baa4118de85aafc56cceeecb59b7.jpg","mimeType":"image/jpeg","putTime":14456620697985018},{"fsize":94280,"hash":"FumgyRZshGyFt1_aRya3GBUJZerg","key":"girl_b_img-8292e5783f8aba0e63be28da6860792c.jpg","mimeType":"image/jpeg","putTime":14456620702169707},{"fsize":32838,"hash":"FrYOIIDIP0iMLXE_puGe3-lwziwn","key":"girl_b_img-8352ee21da857b3fa3401531ddc83667.jpg","mimeType":"image/jpeg","putTime":14456620708842139},{"fsize":38889,"hash":"FjEP8msNVHKvES8V02fG8z1JcaJ2","key":"girl_b_img-8429c126c93db0e75ae3e2b149e6868c.jpg","mimeType":"image/jpeg","putTime":14456620713442797},{"fsize":44754,"hash":"FnWhv36fCT2Q9Nm_NTamIrPfK1V_","key":"girl_b_img-8518aecef23f018070751a79d43b4657.jpg","mimeType":"image/jpeg","putTime":14456620717254254},{"fsize":151892,"hash":"FibLlct3dw1iPoyjk1CUf6oB-R33","key":"girl_b_img-9343e531869cd33819c9df9ff2c8f592.jpg","mimeType":"image/jpeg","putTime":14456620726365747},{"fsize":95533,"hash":"FkBxpZEddnKGCYGZolffx1E2mnJ6","key":"girl_b_img-9377fe154537b390367b70015529f413.jpg","mimeType":"image/jpeg","putTime":14456620735135590},{"fsize":44316,"hash":"FpjVdfmMZsa5tQm1Cdm8PxiGEJoO","key":"girl_b_img-9477c76b910e654c8332993ccd8d1024.jpg","mimeType":"image/jpeg","putTime":14456620738419319},{"fsize":49874,"hash":"Fsxt73-V2BoHWhZnIu3V4VvDfvgT","key":"girl_b_img-9518f9e028d62c9a8ad8b4fba0f19205.jpg","mimeType":"image/jpeg","putTime":14456620741268231},{"fsize":214445,"hash":"FpGhRxR33duQYKeb0CJlkiDIGdVg","key":"girl_b_img-9608e78cf8f67c0fb230ab239369d0ac.jpg","mimeType":"image/jpeg","putTime":14456620755105810},{"fsize":217647,"hash":"Fj_yE90tj2EIhaK6OCNdtmh5iXbV","key":"girl_b_img-14853f5fa101ddcc48e8703c55c445f7.jpg","mimeType":"image/jpeg","putTime":14456620765196456},{"fsize":326915,"hash":"Fjg1tlLicsBI2ZT-j0DO7ICDuuvM","key":"girl_b_img-20709c7e6efd63a3cfcc45955f812be8.jpg","mimeType":"image/jpeg","putTime":14456620785732172},{"fsize":78150,"hash":"Fkuk_E5thdR5LDdoZSFFknXWH3HR","key":"girl_b_img-22061e37bf7e6db7b8e28d584e040903.jpg","mimeType":"image/jpeg","putTime":14456620790424623},{"fsize":361505,"hash":"FsXJLrOdcfvbMoXsgW1p5hgihCj6","key":"girl_b_img-0026621ce20037cf5a25e14cec23f7e8.jpg","mimeType":"image/jpeg","putTime":14456620813527156},{"fsize":92077,"hash":"FhPp1yR9Pohgrc-B2djEK6Alu85u","key":"girl_b_img-28885d072fbb1ef6470f83286085de1e.jpg","mimeType":"image/jpeg","putTime":14456620819824631},{"fsize":149180,"hash":"Fjh92Ofrf3CD_Hrt9VZsQgMplZen","key":"girl_b_img-33347c8be64d9e8538fa70f2e09f13cb.jpg","mimeType":"image/jpeg","putTime":14456620828686104},{"fsize":69714,"hash":"FkfzFkRastT9JaaGE-2cIsOLqbAd","key":"girl_b_img-34821bbab8952a301474b8107cbbebb6.jpg","mimeType":"image/jpeg","putTime":14456620832677722},{"fsize":39521,"hash":"FiRMlf3tnV6qSHqHYgI84l4K-zzc","key":"girl_b_img-39516bae59ee1fb2321138294743a9f8.jpg","mimeType":"image/jpeg","putTime":14456620835835925},{"fsize":55142,"hash":"Fmxl4G0-OnDwAUOcR3IiapKdlMLp","key":"girl_b_img-43498c193e4daf3b6216dcf271f31eed.jpg","mimeType":"image/jpeg","putTime":14456620839182225},{"fsize":87294,"hash":"FjZe8BSqFwV20RqPlMOrXnobESqN","key":"girl_b_img-53864bdda3899f3785eba16195d7b84d.jpg","mimeType":"image/jpeg","putTime":14456620852873556},{"fsize":118316,"hash":"Fv7_t-cnGBf8GxvfOzslyzPOikmb","key":"girl_b_img-069908f2edaedf51479bab8ef40ae31e.jpg","mimeType":"image/jpeg","putTime":14456620863971382},{"fsize":472270,"hash":"Fi83iIjd7suDwzWkM_khhlteNTDy","key":"girl_b_img-70075f43411890473719f70c069457fd.jpg","mimeType":"image/jpeg","putTime":14456620894063647},{"fsize":192509,"hash":"FtEZRnHf4J2qCFCfzUAvmBIvfvoR","key":"girl_b_img-70778ab6ed75de461cde2ebb3d86a491.jpg","mimeType":"image/jpeg","putTime":14456620911408875},{"fsize":66701,"hash":"Fk5U-mswp3HQTRfNrBuecPN2IoPf","key":"girl_b_img-72733a75eba7562627b58e9bcdebbaac.jpg","mimeType":"image/jpeg","putTime":14456620922172584},{"fsize":98255,"hash":"Fm6L2yBcWJPhctVYlRd3N4q9EIR9","key":"girl_b_img-77214ee6d7ded534f778b19533b8d407.jpg","mimeType":"image/jpeg","putTime":14456620928452770},{"fsize":62586,"hash":"FqX8WyNVjsKG8hbpi0X_UkVfaA6e","key":"girl_b_img-77396a1bee71bc12f82446009792db6e.jpg","mimeType":"image/jpeg","putTime":14456620936297947},{"fsize":148634,"hash":"FuWFceWbX2vf7VYkJF0NGitizUv_","key":"girl_b_img-79890e56eea8796fff6cd95e2856b0b3.jpg","mimeType":"image/jpeg","putTime":14456620954856873},{"fsize":145814,"hash":"FjNgBhcI3eo4s0WBVLYhiv62ylzn","key":"girl_b_img-84786f2f78ede0fc35561fc13d927a0e.jpg","mimeType":"image/jpeg","putTime":14456620977383078},{"fsize":212049,"hash":"FmZhpbiTGoTO3e7XciluBgWnMaD4","key":"girl_b_img-88526de7d4adeee1020640c48527240b.jpg","mimeType":"image/jpeg","putTime":14456620998946773},{"fsize":186561,"hash":"Flqz869yCC7l_Uxxx_M8eeAQG7eK","key":"girl_b_img-93950ec9d16e25474cb6bafe6c067913.jpg","mimeType":"image/jpeg","putTime":14456621019302412},{"fsize":97641,"hash":"Fl7T5squW1R4mS7RBZTE2iGNDC5g","key":"girl_b_img-94332d6af74534056d3e15e632645ec7.jpg","mimeType":"image/jpeg","putTime":14456621023935158},{"fsize":40669,"hash":"Fvmjcn503OBixpW-sc5z7KgWyKHG","key":"girl_b_img-94334a8a05d92550174a2dd00075033a.jpg","mimeType":"image/jpeg","putTime":14456621027731383},{"fsize":2983633,"hash":"Fpk-YljG7WWIPdFHy_F3z1O2wZJd","key":"girl_b_img-94369cf43ce76238469885d6cac162e6.gif","mimeType":"image/gif","putTime":14456621218966016},{"fsize":113981,"hash":"FuBNoGIBdGyo08FRgs0izK8WeDnF","key":"girl_b_img-95835fab47634e714bfa9c580277ef3c.jpg","mimeType":"image/jpeg","putTime":14456621227701943},{"fsize":112174,"hash":"FjTTGYMPi52R_FuLnVM8W1xGaqwh","key":"girl_b_img-96804a91cbea2d024ae6447db0dbc502.jpg","mimeType":"image/jpeg","putTime":14456621236486294},{"fsize":88996,"hash":"FjpEceo2jZdfsvoPh-i5wrkEzhI8","key":"girl_b_img-97706f4829fda82c91302f35da0211bf.jpg","mimeType":"image/jpeg","putTime":14456621248375879},{"fsize":24869,"hash":"FpFdc-cWyg2j2gEOSiRtOt7nRIH8","key":"girl_b_img-099189ffaae0aa6624ddb3cf2431894f.jpg","mimeType":"image/jpeg","putTime":14456621254261207},{"fsize":40414,"hash":"FlnlahiwBB_E7rTJloSj2lD8h96x","key":"girl_b_img-157449a1cc4fc9e433fd08d69a8e312f.jpg","mimeType":"image/jpeg","putTime":14456621258244382},{"fsize":243059,"hash":"FoYd_bPQnGPqE8QzcoOxNdkWsa8I","key":"girl_b_img-0310883ce8e7d493ab771e4229634ca8.jpg","mimeType":"image/jpeg","putTime":14456621277910695},{"fsize":73874,"hash":"FprYSTQuLgOXDSG40GXgx38olWbc","key":"girl_b_img-505181b05e44d273343447ab9adb993b.jpg","mimeType":"image/jpeg","putTime":14456621283557220},{"fsize":145981,"hash":"FtdqOEc9JNhNVyO773AwQpiA9eea","key":"girl_b_img-512340f72e288dfa5b9ffb7591408f1a.jpg","mimeType":"image/jpeg","putTime":14456621291488313},{"fsize":9710324,"hash":"lsjDg79yvCxypwALwixyekk7x333","key":"girl_b_img-0644788f85064679e99012c9a5be9ac3.jpg","mimeType":"image/jpeg","putTime":14456621887596118},{"fsize":136899,"hash":"FqqjDnv3rAG9Ok8_h9UxC6beyPU3","key":"girl_b_img-654968d21f8df700506aa0edd480bdff.jpg","mimeType":"image/jpeg","putTime":14456621895013256},{"fsize":557100,"hash":"FjPEkOJNdfFhvuBz16WZM8Cx2au7","key":"girl_b_img-717728d44551138c917d6c5681eac48b.jpg","mimeType":"image/jpeg","putTime":14456621917716427},{"fsize":71299,"hash":"Fg0bXimTOSarjeg2UFFbqRirHrRD","key":"girl_b_img-752253b0fd7cc4c873e95ec4c9345df0.jpg","mimeType":"image/jpeg","putTime":14456621925340694},{"fsize":494713,"hash":"Fte7m6iQDdICEMIGDmIF2j9v0aW4","key":"girl_b_img-767098fa63d212739f62fa897e6b73d7.jpg","mimeType":"image/jpeg","putTime":14456621961528592},{"fsize":128663,"hash":"FnXP0EN2xsrDXXPKEH63l0__Le5n","key":"girl_b_img-812503d432d91a918b51497c2990121e.jpg","mimeType":"image/jpeg","putTime":14456621968230296},{"fsize":462005,"hash":"Fgxgb4NRxV5I6xF1L28GCJjjzwsx","key":"girl_b_img-880568d938e71b53e7f380987e430db0.jpg","mimeType":"image/jpeg","putTime":14456621990100706},{"fsize":91575,"hash":"FsmkNT8TPWIPcZFF5iWGTooIqoQk","key":"girl_b_img-891969c6da4597f25c1a9259bb778b8e.jpg","mimeType":"image/jpeg","putTime":14456621996844700},{"fsize":57797,"hash":"Fsz4y3exjdS8cOPVe-0Y33nJpZ3s","key":"girl_b_img-01175423cddfb54ac9950dadeb4e51ae.jpg","mimeType":"image/jpeg","putTime":14456622000364083},{"fsize":7792819,"hash":"lqMTrciHQxRn1gfV2WhGU4hQvmB0","key":"girl_b_img-1773769d88989a20fd2ee1f4ce738871.gif","mimeType":"image/gif","putTime":14456622471184626},{"fsize":88401,"hash":"Fqrz8Rm9qfSb8qdpphlw0bHSV-KR","key":"girl_b_img-1917339a246c336af5945d7b68a2876d.jpg","mimeType":"image/jpeg","putTime":14456622477414764},{"fsize":119089,"hash":"Figd58VwFti2K8LJ6GiDk83YUsRD","key":"girl_b_img-2758143c5192d3d4f4a4a674828f009f.jpg","mimeType":"image/jpeg","putTime":14456622489115015},{"fsize":93597,"hash":"FqManDxhsE1bc15-DRdsPuwLtG7i","key":"girl_b_img-4167004af9c357a81b1c668b0961018e.jpg","mimeType":"image/jpeg","putTime":14456622495715956},{"fsize":218005,"hash":"FtuYb5Mqxo4pE47shLwL5jcX4jgN","key":"girl_b_img-4628602af52553a1a635f717a7fa7aac.jpg","mimeType":"image/jpeg","putTime":14456622509591617},{"fsize":173110,"hash":"Fj1AjvAcJev37TeMs_U64p1EaNpi","key":"girl_b_img-6101500a79edbf355c2790b3177ad04c.jpg","mimeType":"image/jpeg","putTime":14456622517791798},{"fsize":498115,"hash":"FqhMbnK5WSvIccr6_8E2_P83zA05","key":"girl_b_img-9701232ffe1a5d37fd094abe621f329e.jpg","mimeType":"image/jpeg","putTime":14456622549471325},{"fsize":87668,"hash":"FpcawVmx8-AKEQvbTRjtuy_054Pl","key":"girl_b_img-48603663e7642ccf7844dc82e6fe4d8f.jpg","mimeType":"image/jpeg","putTime":14456622554709341},{"fsize":453588,"hash":"Fs18B7Pxawx3Nb3gf5UrpoYWIIO6","key":"girl_b_img-52190099bf6d5feb4e12910e53b370e3.jpg","mimeType":"image/jpeg","putTime":14456622589595117},{"fsize":125139,"hash":"FhbeBBu8tN8NP23-6tCdPkrkhmtK","key":"girl_b_img-76429426a87e2dff1903ca1485246e83.jpg","mimeType":"image/jpeg","putTime":14456622601421864},{"fsize":771526,"hash":"FrzN3wsx81d9UboNfcXB-7hb7SNh","key":"girl_b_img-91556670fd078ef4335ecc522f2ac425.jpg","mimeType":"image/jpeg","putTime":14456622646979662},{"fsize":31050,"hash":"FnxY_Ui6iN-NKrazFkTdS6eS7toC","key":"girl_b_img-388272777eb8abb15766b8096dd13c5f.jpg","mimeType":"image/jpeg","putTime":14456622651453071},{"fsize":2836088,"hash":"FlOuvAhjyCRm4-GAPTqeXBCo0Ip7","key":"girl_b_img-00512377121e507e20f17f0089dd131a.gif","mimeType":"image/gif","putTime":14456622873197622},{"fsize":455170,"hash":"FiiGsSPAm-1fASBg5wN1f64Iy8fH","key":"girl_b_img-2854012576eac72b6f1053897e0b48a0.jpg","mimeType":"image/jpeg","putTime":14456622910159276},{"fsize":1806875,"hash":"FrRXiishhukNHgnov4E9X3lwkLBq","key":"girl_b_img-4301120249d20aef92fc6694ce5dc4aa.gif","mimeType":"image/gif","putTime":14456623094505192},{"fsize":176786,"hash":"Fq-UIxtFh9KMfe7D7So1saNEPgbH","key":"girl_b_img-6297451128eb497414ee3e6b6bc28a35.jpg","mimeType":"image/jpeg","putTime":14456623107556435},{"fsize":386187,"hash":"FpVKBwkMt7qXTPidi5PjapLxQjaX","key":"girl_b_img-7423016775d947bc9afb2c819ad68556.jpg","mimeType":"image/jpeg","putTime":14456623142617995},{"fsize":82742,"hash":"FsmQ9Sah1ixTf6PKydLBiS-aUGAu","key":"girl_b_img-44333083449f3073d007b4a8dcec161b.jpg","mimeType":"image/jpeg","putTime":14456623148294040},{"fsize":129487,"hash":"FohNLDZMj8TmR0raVqEO8VNPRYhC","key":"girl_b_img-67767586570e909880142d807ad7bc2d.jpg","mimeType":"image/jpeg","putTime":14456623164490534},{"fsize":58326,"hash":"Fvvfsd-hBz9t3Dt929yIWX_fQiBs","key":"girl_b_img-600437845651af7fb249068df2af1fee.jpg","mimeType":"image/jpeg","putTime":14456623176470340},{"fsize":66783,"hash":"Fv_q__puQsJPRRLbXT04-3aldsbM","key":"girl_b_img-1813627601731ce08df5b4ef37fef1f4.jpg","mimeType":"image/jpeg","putTime":14456623181542092},{"fsize":154032,"hash":"FrVzVuAORUyZvdI96KfOIu0uglGW","key":"girl_b_img-a2f10ad729938613c570d1cec82a5569.jpg","mimeType":"image/jpeg","putTime":14456623196696591},{"fsize":127906,"hash":"FqSpNgsYzWI_G6ncQAMfRkqbLny7","key":"girl_b_img-a3dc0f60bafdf6b0afda50a25d0abfee.jpg","mimeType":"image/jpeg","putTime":14456623212498806},{"fsize":256799,"hash":"FsYypaba0G-RdpEWfWk5LyXrPOZA","key":"girl_b_img-a3f0e115e1dae64134a7cec07d67494d.jpg","mimeType":"image/jpeg","putTime":14456623247749885},{"fsize":71178,"hash":"FnZ5nr3hCT4qyp2lyfqQ1DHq5Qvm","key":"girl_b_img-a4a35231186b1ee187d57de809a428f7.jpg","mimeType":"image/jpeg","putTime":14456623257373721},{"fsize":54332,"hash":"FiDe7hBuYTAg9S6Mp36Wvn9f1M3l","key":"girl_b_img-a4c09ef04e17f9f481403dbb7520f1a0.jpg","mimeType":"image/jpeg","putTime":14456623262325522},{"fsize":70823,"hash":"FvrDIblLm2g6DvInmOVeO0-sYxJl","key":"girl_b_img-a4da11de77114c8cb2da601734ec2522.jpg","mimeType":"image/jpeg","putTime":14456623268521966},{"fsize":116318,"hash":"FlbJD5LmWd2fgSD3wUaFM06DGBQe","key":"girl_b_img-a5ad93634135cd596a6efdf485bd8a90.jpg","mimeType":"image/jpeg","putTime":14456623281878585},{"fsize":50312,"hash":"FnTpQAyOZdnzbrRyT25k-lJpYQnz","key":"girl_b_img-a38a89f7944c3a5828c4bc6efa54347c.jpg","mimeType":"image/jpeg","putTime":14456623286686054},{"fsize":249479,"hash":"FgWsV4scAHk1q9XARIRWPIqOgRP6","key":"girl_b_img-a68e9d65a5e83e310c09dca05d80bca2.jpg","mimeType":"image/jpeg","putTime":14456623317759044},{"fsize":765525,"hash":"Fh5Aq7RtKwS5AZ9sWRIx0zYwG12g","key":"girl_b_img-a94a571c75331ab02a96328e8981665c.jpg","mimeType":"image/jpeg","putTime":14456623400744749},{"fsize":71554,"hash":"FqB6Gsn9PXb6EKugPmMN9UMGcCds","key":"girl_b_img-a0750d8064b48b3187b51783cc260fba.jpg","mimeType":"image/jpeg","putTime":14456623405557319},{"fsize":107515,"hash":"FkPVOc_ujPoxT4DP5uvSpw1jXpk8","key":"girl_b_img-a753b1d16e9e9e146709c82b3b48e887.jpg","mimeType":"image/jpeg","putTime":14456623418757888},{"fsize":5047805,"hash":"lpkkNJdUOxEsQt0xxWbEsVXzG9Ew","key":"girl_b_img-a5113ff3b8c9b5641ae95b003d685e7b.jpg","mimeType":"image/jpeg","putTime":14456623835441395},{"fsize":146929,"hash":"FkC6J8Vz8zJil3EWSveZEppvdTy9","key":"girl_b_img-a6483af4a6ba63a16f9205b58a3ce311.jpg","mimeType":"image/jpeg","putTime":14456623848248612},{"fsize":86765,"hash":"Fu3Jy8PqK5j6ix9QxtuSLFH-Z817","key":"girl_b_img-a8211f0392b9319e61aa88111dec2876.jpg","mimeType":"image/jpeg","putTime":14456623854966544},{"fsize":3269766,"hash":"FkMiE8sdbS0Ht5c9ygysi9w3Agei","key":"girl_b_img-a18613c7c48f2aede7a305a665b4139d.jpg","mimeType":"image/jpeg","putTime":14456624133462986},{"fsize":120064,"hash":"FhbAQuin6yZa29j8xRAt6npRyNpN","key":"girl_b_img-a985894c093d6db966bad70fe0a92c05.jpg","mimeType":"image/jpeg","putTime":14456624151541899},{"fsize":423909,"hash":"FvNACsh9OiplTGH37cKnN-YvMf4F","key":"girl_b_img-a5706686f848bc651e7194d0a8cf1dd5.jpg","mimeType":"image/jpeg","putTime":14456624201220846},{"fsize":56616,"hash":"FgUnIj7ThrYVX-m9lgN1pWvOfG-9","key":"girl_b_img-a64896815648c627eb46bfd8503333f7.jpg","mimeType":"image/jpeg","putTime":14456624215095423},{"fsize":799312,"hash":"Flub3I8X37MO5w3YCktKRkA4ULss","key":"girl_b_img-aa02154389c52a77a94bba706b9cd5f4.jpg","mimeType":"image/jpeg","putTime":14456624320111391},{"fsize":240630,"hash":"FoJ5F1Pdg3X_csYCNhR1sKfwTu4k","key":"girl_b_img-aaa37967c9148276aa76df22e3c86bcc.jpg","mimeType":"image/jpeg","putTime":14456624340087937},{"fsize":100428,"hash":"Fjq8SEg5q_ieXEKbEk8-WA4uTpw1","key":"girl_b_img-aaf7496393c10b98e8306c3f7a070c4b.jpg","mimeType":"image/jpeg","putTime":14456624357578503},{"fsize":84008,"hash":"FlxjuaL-aA5EQ5z4jHxMpDS_3nfq","key":"girl_b_img-ab6f5d92c0060ccf867db52187622fb7.jpg","mimeType":"image/jpeg","putTime":14456624367881455},{"fsize":45712,"hash":"FlUcV6_VLUFRXVP8Iov3JZkOSU33","key":"girl_b_img-ab83adb8ef82befc28944507e0c97db5.jpg","mimeType":"image/jpeg","putTime":14456624381741992},{"fsize":117648,"hash":"Fm2VPl9peVPXmvUM6ZflOC34-OyC","key":"girl_b_img-ab109bc9a87390cd53ce332ab4b01ef5.jpg","mimeType":"image/jpeg","putTime":14456624390632785},{"fsize":175061,"hash":"Fhk-1g40dOPPYbIoP11dyfbKHZwZ","key":"girl_b_img-ac87db53223e15c00ad91f09a3258b8e.jpg","mimeType":"image/jpeg","putTime":14456624402832829},{"fsize":141052,"hash":"FoTFXO5_JUcEWHbtLrvZqjJxEgBS","key":"girl_b_img-acc8ddc59d9cbd0ec6aaad98e21f485f.jpg","mimeType":"image/jpeg","putTime":14456624411125870},{"fsize":94384,"hash":"FmepY7v2IggeCmoDbedh46_j_QXG","key":"girl_b_img-ad511ecda42b4e7d7decea08705f449a.jpg","mimeType":"image/jpeg","putTime":14456624423304200},{"fsize":1825683,"hash":"FrvdXk94M-zEG835dcxqRw--L82b","key":"girl_b_img-ad4989f3044e44c4feefebe0e4ef1d74.gif","mimeType":"image/gif","putTime":14456624711488386},{"fsize":73934,"hash":"FpwyOCUFRxnuZCOhvka5kshmdAVH","key":"girl_b_img-ad1893321623ef1bd5796d83b1222a8d.jpg","mimeType":"image/jpeg","putTime":14456624717915495},{"fsize":35792,"hash":"FvOnjVDpd5oVSXahz6jfIhQq3fYS","key":"girl_b_img-aefc412e1a867c7a8810834f317be91c.jpg","mimeType":"image/jpeg","putTime":14456624738368752},{"fsize":59453,"hash":"FqymDXzFWCxi-KhI0siiuEVb36T_","key":"girl_b_img-aefe7f0fbc1de31ce488ad785103eab2.jpg","mimeType":"image/jpeg","putTime":14456624766192158},{"fsize":3682944,"hash":"FsFbInBZizF8vEv0SQ2ad1_0u10t","key":"girl_b_img-af3a333f1423430666b98159d9bf8d65.jpg","mimeType":"image/jpeg","putTime":14456625218050430},{"fsize":159927,"hash":"FgbP9iLxcnLvLgWdxmK1MhsvkxBx","key":"girl_b_img-af965d8a58d9ba90c6d5fcc5b5104e6e.jpg","mimeType":"image/jpeg","putTime":14456625239989952},{"fsize":104675,"hash":"FsSwr8kgyeneZNmc-siHe3FvN6Gr","key":"girl_b_img-afda1c67c6d8db4cb07277a85ad2bec8.jpg","mimeType":"image/jpeg","putTime":14456625259908036},{"fsize":1952069,"hash":"FlocYca9yyrfuPvyWUTZZ1uBsMGo","key":"girl_b_img-afe6fb25d39578f50e36621bfbdf8248.gif","mimeType":"image/gif","putTime":14456625404529007},{"fsize":180132,"hash":"Fq_tlTkx9svv9Gidu7JHS-GffMDh","key":"girl_b_img-b0f6745d493aef76c0879d9b4dcf8616.jpg","mimeType":"image/jpeg","putTime":14456625423823049},{"fsize":144268,"hash":"Fj4ScBMDoipXsZzItqQEzU0P7KCp","key":"girl_b_img-b1a7c173fe3ab76b482bfc547b0a0a13.jpg","mimeType":"image/jpeg","putTime":14456625435762230},{"fsize":192537,"hash":"Fj68mv1X5A7oI6shVeLl5Pp1FC-3","key":"girl_b_img-b3c2f771e511ec37e508030357cf3b76.jpg","mimeType":"image/jpeg","putTime":14456625450631454},{"fsize":23161,"hash":"Fg5O5fGYfgfAoOQCcKWV1Ao_vNTk","key":"girl_b_img-b4d02d57d346a0c34fe269c415dafdf1.jpg","mimeType":"image/jpeg","putTime":14456625453431738},{"fsize":143039,"hash":"Fi5oVqYnOlKYtO17mWaEYcjxOgpq","key":"girl_b_img-b5cbf5aecd64b8365cfdbc4606ffab60.jpg","mimeType":"image/jpeg","putTime":14456625467853995},{"fsize":733028,"hash":"FqWMtuBXQDmGfQ6l9978MWtD4SjI","key":"girl_b_img-b6a59308f3585a1550a2dceee4c36b3b.jpg","mimeType":"image/jpeg","putTime":14456625508757436},{"fsize":43733,"hash":"FsyCm5CYZJjDmywWGS9f_iOWCM8J","key":"girl_b_img-b6efe8bec96906b5ee633d65ea21b42a.jpg","mimeType":"image/jpeg","putTime":14456625515145982},{"fsize":99301,"hash":"Fn-xbwBpwITHwS4FZvAlxJ_rRhMN","key":"girl_b_img-b08e884a8f6a587b9085e1812bd76f9e.jpg","mimeType":"image/jpeg","putTime":14456625523558598},{"fsize":19588,"hash":"Fp4HN3XmD5oq0DT-YAj1VhTyYv-R","key":"girl_b_img-b8e04a9314b6383f1670e80ef0edd57a.jpg","mimeType":"image/jpeg","putTime":14456625536318097},{"fsize":50705,"hash":"FkxmLcdPVZaiWb1nYxUsvXAdAz0V","key":"girl_b_img-b9d7d3869d0dc6c0fa9ee06d3c365d3c.jpg","mimeType":"image/jpeg","putTime":14456625543809920},{"fsize":109338,"hash":"FoM3bJA_CV0uuElM7dxZk4abbd9S","key":"girl_b_img-b31a11436f8449a13330c62597d615c3.jpg","mimeType":"image/jpeg","putTime":14456625566944903},{"fsize":131064,"hash":"FlX6VAbPTOSXp56UKupOutQJMwB8","key":"girl_b_img-b49e370df283b72e1136c9cd9fcb9f52.jpg","mimeType":"image/jpeg","putTime":14456625583671444},{"fsize":68009,"hash":"FvOYZ9Tg41yEGshGJJr64z1K1nmz","key":"girl_b_img-b248a9089214fae5c8c5aead5774f1eb.jpg","mimeType":"image/jpeg","putTime":14456625588568826},{"fsize":28652,"hash":"FoPBoLTNs9efQNdYYf59P-Yw_UgH","key":"girl_b_img-b4226e314cddbe25541d31b1bcc94af4.jpg","mimeType":"image/jpeg","putTime":14456625591429582},{"fsize":48622,"hash":"FqQDL672fyTJpiYNc2C4pAHX7Pdh","key":"girl_b_img-b05787e165cdf73e87567747530319cf.jpg","mimeType":"image/jpeg","putTime":14456625602060353},{"fsize":35361,"hash":"FjFr9XwdfEA8xOmdFSmEDygiBG27","key":"girl_b_img-b6746c73c05b7ff93bfdd75b2e838513.jpg","mimeType":"image/jpeg","putTime":14456625605343922},{"fsize":2328819,"hash":"Fivo_yogsYX-58l4Pn7Nr6bBZc92","key":"girl_b_img-b79301f96d19acf650b3023619578ede.jpg","mimeType":"image/jpeg","putTime":14456625798428497},{"fsize":1320029,"hash":"FrghEx_65qYUkhOWW9Ay1pVxaXpp","key":"girl_b_img-b89242f1b244d29ea56ffec798e63110.jpg","mimeType":"image/jpeg","putTime":14456625897987783},{"fsize":67608,"hash":"FlloVTy55b6q-xjo0VtPobxeZ1Wg","key":"girl_b_img-b59141197754c215c8bdf01e76d1c862.jpg","mimeType":"image/jpeg","putTime":14456625909618941},{"fsize":274240,"hash":"FqbtNI6sKyrNcLubGh2IJxPgOMbh","key":"girl_b_img-b151313153244cf2b65f598d9d9e0e4c.jpg","mimeType":"image/jpeg","putTime":14456625934360131},{"fsize":99076,"hash":"Fh1EESxM45D7gOxy00bXLs35c1e1","key":"girl_b_img-bab4abc563e99aeadd304341c60bfb4e.jpg","mimeType":"image/jpeg","putTime":14456625940787053},{"fsize":73451,"hash":"FgyQUYZR-erI3eZO9labFDzI5mzw","key":"girl_b_img-bae4df3d3266eba49bc0d733b2bc057d.jpg","mimeType":"image/jpeg","putTime":14456625953735421},{"fsize":695472,"hash":"Fjx0PMzdmJd6NOKDSh41qul5B-wE","key":"girl_b_img-baff53230dc2f971209439d105e662c2.jpg","mimeType":"image/jpeg","putTime":14456626027202328},{"fsize":195479,"hash":"Fi5ZsvyDp6tD5RDTJ6tzNgzFE12_","key":"girl_b_img-bb3c9329ca6fba34039bd6b63601d5f7.jpg","mimeType":"image/jpeg","putTime":14456626062686476},{"fsize":48796,"hash":"Foheu9BmoA23l2HvwV12uOXhDK-3","key":"girl_b_img-bb7cb13b591302c51bf7bba36d9b033e.jpg","mimeType":"image/jpeg","putTime":14456626067073918},{"fsize":46903,"hash":"Fgh0nhl1yooaqc-k_7T9LaLfkTGd","key":"girl_b_img-bbe5b7429635e636ed205739e119b220.jpg","mimeType":"image/jpeg","putTime":14456626075781888},{"fsize":175395,"hash":"Fqwyj_stztIey_DB2SGDNyur4zIf","key":"girl_b_img-bbf0f1779d0e2bf19d7c2e0074d1c3e3.jpg","mimeType":"image/jpeg","putTime":14456626087175353},{"fsize":3440256,"hash":"FkcxeovcDnmRkm6KL2t9bIzxemYY","key":"girl_b_img-bc8b5e929791c5868568efa7ba1f68f0.gif","mimeType":"image/gif","putTime":14456626449150341},{"fsize":23623,"hash":"FjiXmXIx-BJ0p6RwQjVTC62wijsz","key":"girl_b_img-bc826c339a7f0a4e609e4255fdc48425.jpg","mimeType":"image/jpeg","putTime":14456626455119560},{"fsize":133561,"hash":"FnXAFPw_ixavbxA9m_XFJgMxWT5R","key":"girl_b_img-bcc382b62a1c1091112c456c0396ba5a.jpg","mimeType":"image/jpeg","putTime":14456626461405955},{"fsize":123554,"hash":"FuA-otAOf3x_4Y75SLCyNrfZQ02W","key":"girl_b_img-bd3d5b321eec96d695ef7967a74a8284.jpg","mimeType":"image/jpeg","putTime":14456626468214444},{"fsize":197698,"hash":"Fg5yVM8nIAzQhI3q6RT_oK6Vk-uW","key":"girl_b_img-bd20fa4ea179da817d03170a40e6bd62.jpg","mimeType":"image/jpeg","putTime":14456626481983573},{"fsize":22646,"hash":"FqI2N8dWBBdcCuQhdYoS10YorDcd","key":"girl_b_img-be9cdefc66d5f89c62b7e5c0184622bd.jpg","mimeType":"image/jpeg","putTime":14456626484408084},{"fsize":140317,"hash":"Fr1wQ2L2YAi0Ee05ac0Zbiyi7XKw","key":"girl_b_img-be0961f342cf4cd775d9a9efab883898.jpg","mimeType":"image/jpeg","putTime":14456626494634520},{"fsize":39365,"hash":"Fl1w-39KkrCIjAU866RWlU5mur-u","key":"girl_b_img-be34172cce0a344c7bbb61df8ccd495c.jpg","mimeType":"image/jpeg","putTime":14456626497534503},{"fsize":114862,"hash":"Fh91XadKQtK15pv9XjtvfH3yVwNX","key":"girl_b_img-bec0ac2ab4f6d4dc87f32f4fd21fcb1d.jpg","mimeType":"image/jpeg","putTime":14456626504097002},{"fsize":106084,"hash":"FklF04R0M6seAcf1BzL6HJiYMS-G","key":"girl_b_img-bf884ad1a2752bc5945b5fd3fb8e4b60.jpg","mimeType":"image/jpeg","putTime":14456626520982936},{"fsize":111692,"hash":"FkT5m5AB-lbz9U2kWw9KWvJERHsT","key":"girl_b_img-bfb10e483a106190679c3e1acb98667f.jpg","mimeType":"image/jpeg","putTime":14456626529914034},{"fsize":151662,"hash":"FvGMZqiTY0MQseLIQAEif4iFqGjK","key":"girl_b_img-c0dc6b4c7369985e6cd76d0abd1fcdd3.jpg","mimeType":"image/jpeg","putTime":14456626539193143},{"fsize":156192,"hash":"FhAf_maw9JXJ-rwnKmvhCeq4isdc","key":"girl_b_img-c1f35731f03b0115e3a9a6948fad2682.jpg","mimeType":"image/jpeg","putTime":14456626551383295},{"fsize":125553,"hash":"FuNP18lWchviEn5vrj2TOUzO6I-3","key":"girl_b_img-c2db01f5751c90b5020c33277dc5dffc.jpg","mimeType":"image/jpeg","putTime":14456626558995386},{"fsize":58170,"hash":"FiVeUKlPu6C3-AAwN9tBM5tH6yAZ","key":"girl_b_img-c3ee56120fe84a7305685c1fbea43320.jpg","mimeType":"image/jpeg","putTime":14456626566823200},{"fsize":1418414,"hash":"FrU0NVMElDhfKfHoPX5bMie2t3BE","key":"girl_b_img-c7fbaf541c8b36a0eace5f53efde80a3.gif","mimeType":"image/gif","putTime":14456626656693462},{"fsize":152306,"hash":"Fu7_icKM1XDfjHfTK-wsZ3YyoYkr","key":"girl_b_img-c9bd48a8fb32e19553cc2f12edc9d134.jpg","mimeType":"image/jpeg","putTime":14456626675353189},{"fsize":5154105,"hash":"llLA7VsC77iVXdxDs-HazFeB8SpL","key":"girl_b_img-c19e7718f82a9d86642461442a02124f.jpg","mimeType":"image/jpeg","putTime":14456627292331396},{"fsize":87143,"hash":"FnLak8zPnubbIyl3-bjPqkFNSf8l","key":"girl_b_img-c20f42f4b7ec35426468791b910b757c.jpg","mimeType":"image/jpeg","putTime":14456627301492450},{"fsize":162503,"hash":"FtvPvx0ptFw3KyztsSeCfey_68Rm","key":"girl_b_img-c27c33d4aa801a337d65735571ee8119.jpg","mimeType":"image/jpeg","putTime":14456627313937124},{"fsize":1847828,"hash":"Fsp3RcC_gUscqK9324AXWMh7IFkb","key":"girl_b_img-c31f78249568cd72a8a376f40a0c076d.gif","mimeType":"image/gif","putTime":14456627496376204},{"fsize":105432,"hash":"FsHmacZgGW1PtTdoo7Mgv__Ipf0P","key":"girl_b_img-c59ff4fd4764e769158c9ac76df73450.jpg","mimeType":"image/jpeg","putTime":14456627512867552},{"fsize":50527,"hash":"FhnMeAT6c9MR7VQnraP4tdBUtO3Q","key":"girl_b_img-c66c7ecd665876b0a4fb6169f776e27e.jpg","mimeType":"image/jpeg","putTime":14456627516854682},{"fsize":5061328,"hash":"li7ksElASPBx5LjXUOMR7HgTNSHR","key":"girl_b_img-c86c5e5e97fc6aa60611e76b3e4afae8.jpg","mimeType":"image/jpeg","putTime":14456627927322481},{"fsize":298113,"hash":"FkV8HbawcCwm5xCVLcoDQRhashmc","key":"girl_b_img-c525e5e482779f088cf330fcfa412168.jpg","mimeType":"image/jpeg","putTime":14456627945052704},{"fsize":497207,"hash":"Fm4zsbWm9CY59obopjNPS5MmDBlL","key":"girl_b_img-c626d1336e93a6e5f87bd1bc2688e5ce.gif","mimeType":"image/gif","putTime":14456627988903756},{"fsize":289506,"hash":"Fpfed9rmm3Cx-eFdtGKhPbv9mS2g","key":"girl_b_img-c1426e5511920768108c68b59db66faa.jpg","mimeType":"image/jpeg","putTime":14456628005341831},{"fsize":268565,"hash":"FtJuQ7duItCXuFodjzQDHpbjnbRP","key":"girl_b_img-c8115a3df1b896b4bafe39cc6f41582f.jpg","mimeType":"image/jpeg","putTime":14456628021344507},{"fsize":83253,"hash":"Fs847WB54sWd86bxiU7UF410WPbt","key":"girl_b_img-c27103c2c6b6ef4392f14b3ac096e93c.jpg","mimeType":"image/jpeg","putTime":14456628028216663},{"fsize":2548190,"hash":"FqYCw7yH5kYukuxM1Zi4fT_MRQYN","key":"girl_b_img-c31113fdef0a7e6d5e81026061826245.jpg","mimeType":"image/jpeg","putTime":14456628361117111},{"fsize":157177,"hash":"Fg0Pd72DVeIPgavFHyOVMHoeO_5Q","key":"girl_b_img-c704459cc1f217cb4a6f31d1dbfe7044.jpg","mimeType":"image/jpeg","putTime":14456628386505343},{"fsize":48881,"hash":"FkqcNa-NxiqCNkB5UhTfifkUdgl1","key":"girl_b_img-ca0e3b3e8598099ee7bdec9b77de7c53.jpg","mimeType":"image/jpeg","putTime":14456628397140934},{"fsize":93694,"hash":"Fh_u0xl4j8EGrfPQOvzyH0rIVOII","key":"girl_b_img-ca9cfb9ad9fb53b4e3e2d00515770867.jpg","mimeType":"image/jpeg","putTime":14456628432290014},{"fsize":6289614,"hash":"lsX5EhRd0JXzHh5idFlOcBFUDTt-","key":"girl_b_img-ca46ae3d6c1aedc2c538119ba8802616.jpg","mimeType":"image/jpeg","putTime":14456629092959729},{"fsize":29636,"hash":"Fuh-oC4lgJaAI16gv6v_zlbzwI4S","key":"girl_b_img-cad2d18485a51b42907a273f655e1db3.jpg","mimeType":"image/jpeg","putTime":14456629102236829},{"fsize":112940,"hash":"Fv7KM3_OM6kznD2uGV3HOK7-xMmA","key":"girl_b_img-cae6b29ffbc07b2fbf8d27980da20f1f.jpg","mimeType":"image/jpeg","putTime":14456629125663244},{"fsize":37702,"hash":"FhGu5w8nh6MvdJDdw8aPrIP4_gh_","key":"girl_b_img-cb6db849c3ee1f1576116951774c8aab.jpg","mimeType":"image/jpeg","putTime":14456629439094860},{"fsize":2040408,"hash":"FmsEq_P-UZkrMY7vPqRNxbTZEVMX","key":"girl_b_img-cb6044425dcdc9f52fe3ac45af92b3c1.jpg","mimeType":"image/jpeg","putTime":14456629685378538},{"fsize":43716,"hash":"FhlnBMUky1lom68liYk-KanjtSK_","key":"girl_b_img-cbd78c3f6e71b8b22d8420f9fe01ba37.jpg","mimeType":"image/jpeg","putTime":14456629694903485},{"fsize":99060,"hash":"Frv5eZ09lreohKPFR3GdbZNoYiks","key":"girl_b_img-cc0d67ea707b83d21a4700a6e0ae2284.jpg","mimeType":"image/jpeg","putTime":14456629705261488},{"fsize":302323,"hash":"FqOLt7c4qpX-lJwkm6jZ_fIv6zwL","key":"girl_b_img-cc253c8772cbaf9344505f21c288e6ba.jpg","mimeType":"image/jpeg","putTime":14456629719628198},{"fsize":96211,"hash":"Fi7ecE2ccdaKZhaylF9Ob_e-Ewry","key":"girl_b_img-cd3d4e7a971be26aaa9d39c269776aca.jpg","mimeType":"image/jpeg","putTime":14456629729996874},{"fsize":2562980,"hash":"FoTiZatMlXbT6zbNL5tBBtd7kEgp","key":"girl_b_img-cd62926356187f68bbc611e90650b407.jpg","mimeType":"image/jpeg","putTime":14456629907880089},{"fsize":81029,"hash":"Fs0LEq1HaJBo-CC6XFmmHlCAE3fE","key":"girl_b_img-cd3694480675488c812f69249df914d8.jpg","mimeType":"image/jpeg","putTime":14456629915843663},{"fsize":54252,"hash":"Fj6DV7JHgjT10ecDVLZ3qIvX2clm","key":"girl_b_img-ce7b986c9a109e1347e4416297dff61d.jpg","mimeType":"image/jpeg","putTime":14456629919788794},{"fsize":3619755,"hash":"Fk1byBHhZ66uA8Ipstjli4D1o8ul","key":"girl_b_img-ce38c6b70efdb7a336885fa81d544788.gif","mimeType":"image/gif","putTime":14456630329157946},{"fsize":161468,"hash":"Fmil8stf4azYtRIu3yVwRzEblCWM","key":"girl_b_img-ced69d0eb7d11fe5112376fd02791738.jpg","mimeType":"image/jpeg","putTime":14456630345189753},{"fsize":348262,"hash":"FvEHb3rMTEKQbK7aeXYM345i_zWs","key":"girl_b_img-cfc63e6c6ea55d416077af01463012fb.jpg","mimeType":"image/jpeg","putTime":14456630410085696},{"fsize":137730,"hash":"FlctsEbMeKq9VHkIxyqDBgbHhmHo","key":"girl_b_img-d1ab78a5232a4560a4573d4379ac370c.jpg","mimeType":"image/jpeg","putTime":14456630432217026},{"fsize":1453704,"hash":"FounW-HX-3FoO7yOaJmLwqFc3zzS","key":"girl_b_img-d2e9361954fb31d90e4e539aad9f0976.gif","mimeType":"image/gif","putTime":14456630661488370},{"fsize":639291,"hash":"Fny2AHTFhaaPDovRKwhnpLw3eOTv","key":"girl_b_img-d2ef70a2ecc808be82fbdafd5e3e0aed.jpg","mimeType":"image/jpeg","putTime":14456630742872030},{"fsize":123869,"hash":"FoI35Yd6IjfWAcOjX8k50APRnPSc","key":"girl_b_img-d03ebbc18f03e1de2c95c2fdf4d42501.jpg","mimeType":"image/jpeg","putTime":14456630750720765},{"fsize":436799,"hash":"Fvt1WJI4M4KcUPz71lDQIJXlyCN7","key":"girl_b_img-d4b59849934638bd9b52783cf1f370a7.jpg","mimeType":"image/jpeg","putTime":14456630782641725},{"fsize":164851,"hash":"Fpo1I8aSP5zgz26ab0ZG-yodazra","key":"girl_b_img-d5b0e824634191c66f42a45170a95f35.jpg","mimeType":"image/jpeg","putTime":14456630790695098},{"fsize":138438,"hash":"FnKRzNyyNkTIU2HAaFbBtLlG6Elu","key":"girl_b_img-d6b41cb7d58e92b8f638d1b6afe7e8ff.jpg","mimeType":"image/jpeg","putTime":14456630813738372},{"fsize":111756,"hash":"FjsBmTGlJpibjCbfhsro09YU6_-o","key":"girl_b_img-d8a39331e1692d4e4d5ffd93b188379a.jpg","mimeType":"image/jpeg","putTime":14456630883628362},{"fsize":84288,"hash":"FqeUVqC3aBGT9JPGsBVfp7hQVB_4","key":"girl_b_img-d8cf4a0ada3b91cb4e31719c9cb8fea7.jpg","mimeType":"image/jpeg","putTime":14456630903968027},{"fsize":53862,"hash":"Fo1bPcki0d86gk_3juymt_qQkeO_","key":"girl_b_img-d9c5fdc712c1877ffe0f3c00ac9aab69.jpg","mimeType":"image/jpeg","putTime":14456630907840074},{"fsize":655754,"hash":"FqeASHR941PGwRdQoxKZAffviPi5","key":"girl_b_img-d15e6b385330055f030b0dceffe94f49.gif","mimeType":"image/gif","putTime":14456630960473542},{"fsize":146513,"hash":"FrgcufsxJtIZjcHdAeAHmByotEfP","key":"girl_b_img-d36ecb1765cbe30ca0183616017b4d4c.jpg","mimeType":"image/jpeg","putTime":14456630975326779},{"fsize":73268,"hash":"Fsvg0Za550bhyURXG-eAIDywdPIx","key":"girl_b_img-d70c7b06540b6e20dd42247b2ebd9944.jpg","mimeType":"image/jpeg","putTime":14456630983167750},{"fsize":713350,"hash":"FjCP5rRSoptarLf35LBW8h_CS3zC","key":"girl_b_img-d86ae11966d364fb70c03e418351b47f.gif","mimeType":"image/gif","putTime":14456631039703563},{"fsize":33098,"hash":"Fq8w5BpGkagqllIF4UshMFyVjUcg","key":"girl_b_img-d91af91bd83e7eb080837cf604f21f5a.jpg","mimeType":"image/jpeg","putTime":14456631057371557},{"fsize":70085,"hash":"FuQhrFFq-P30DiQ3GFxEWtTWbZJL","key":"girl_b_img-d159bcb676cf160af1b2a1584306d7f1.jpg","mimeType":"image/jpeg","putTime":14456631073993749},{"fsize":82501,"hash":"FpF9LRqte-7ot9axScm9GsWhDQWo","key":"girl_b_img-d197b764a5c8dd85051d93eb4650fb8b.jpg","mimeType":"image/jpeg","putTime":14456631092308517},{"fsize":379504,"hash":"FjT4j4RJ3yaa4gTONhX57Fj0xdNT","key":"girl_b_img-d0366faa699f837902f72d556fe1acd1.jpg","mimeType":"image/jpeg","putTime":14456631208626306},{"fsize":28359,"hash":"FlNooa72U5azfNXbBN6sn88e8HbW","key":"girl_b_img-d821a5349f5711108fa39749fbe201c2.jpg","mimeType":"image/jpeg","putTime":14456631221899716},{"fsize":75890,"hash":"FlyhF9U5GJt4J_vQChrnlnCspcLV","key":"girl_b_img-d1318d5b9f8c102adef77f1c3a09d304.jpg","mimeType":"image/jpeg","putTime":14456631229305058},{"fsize":112262,"hash":"Fk3jfG5r9sK9uw4LekR9bOcVlZPK","key":"girl_b_img-d9566cc6fca344a328de0416b707e929.jpg","mimeType":"image/jpeg","putTime":14456631246236851},{"fsize":706823,"hash":"FvIcXtjZS1pOExVoCf72zOFM0A3b","key":"girl_b_img-d09670d8f438c2410827a14675f62783.jpg","mimeType":"image/jpeg","putTime":14456631299265489},{"fsize":84928,"hash":"Fm_1a-1g5xwjz6hTf7ZuTB3D2pVX","key":"girl_b_img-d57862d9abab09d3028e002e2f2b88bf.jpg","mimeType":"image/jpeg","putTime":14456631311074733},{"fsize":71861,"hash":"FnvBceko_zTA4-f50-h-DmBExB1X","key":"girl_b_img-d374606ebc11a26390d009245ba4779b.jpg","mimeType":"image/jpeg","putTime":14456631332547541},{"fsize":52417,"hash":"FjaOxc0B9ojAWjqHqGoHGr-og42q","key":"girl_b_img-d848685f7f5d0fbb06c2f61d82e19134.jpg","mimeType":"image/jpeg","putTime":14456631336717044},{"fsize":1175444,"hash":"Ftzwr2ya4XVqb9MR0YEFSjN1Vlfb","key":"girl_b_img-d3424312e32abda2282185be06e1cfde.jpg","mimeType":"image/jpeg","putTime":14456631448144555},{"fsize":91082,"hash":"FtL6S_FQUNcjuQXu1rjhgczEPgTn","key":"girl_b_img-d11227398483abcd6db38aeabf432102.jpg","mimeType":"image/jpeg","putTime":14456631458575329},{"fsize":1478368,"hash":"FrGHBi9C4Bh-WSoMYaTx2K2-f-AF","key":"girl_b_img-daff3e83d10dd88e61535a5afee3a054.jpg","mimeType":"image/jpeg","putTime":14456631623943318},{"fsize":3269960,"hash":"Fua5VmEUaxkiWu_Fi5mm2q_QvHNB","key":"girl_b_img-dbc06e59249b48232239c864518af772.gif","mimeType":"image/gif","putTime":14456632096255654},{"fsize":219723,"hash":"Fiw5ufF5qnicegzyF8EDKD4YUkPm","key":"girl_b_img-dbe18cb7f6594f9b80aa3fc2401c7495.jpg","mimeType":"image/jpeg","putTime":14456632117592493},{"fsize":416591,"hash":"FkKtPuQNq512K4WKnt-EnOSmiJAS","key":"girl_b_img-dc16bff2c605207aef1900f0475e9b56.jpg","mimeType":"image/jpeg","putTime":14456632148455496},{"fsize":953419,"hash":"FpX59Kq_tgYYu1Dm1Wgj-k80m7k3","key":"girl_b_img-dc44ed36406dd511ef9ff120c8cc51d5.gif","mimeType":"image/gif","putTime":14456632279720662},{"fsize":66152,"hash":"FhoPu9olzWM5YpFc9A333S_gVF11","key":"girl_b_img-dc90b32e1d31cda994a2e41f9b4fde5b.jpg","mimeType":"image/jpeg","putTime":14456632286021239},{"fsize":104412,"hash":"Fg3158oF1sdZ6YsVbme2TpORYQ8S","key":"girl_b_img-dc427550e2f2a0bded538240c2376714.jpg","mimeType":"image/jpeg","putTime":14456632301636898},{"fsize":309731,"hash":"FtQYqVE9drmijMo6-VRX_HN6N9RO","key":"girl_b_img-dc89991501d8f812e330cca3c402717f.jpg","mimeType":"image/jpeg","putTime":14456632326340107},{"fsize":1743504,"hash":"FnC0uIZdgt7i73iHthMgUAVBF9HI","key":"girl_b_img-ddf5cb4e1a032fd074be79a83389808e.jpg","mimeType":"image/jpeg","putTime":14456632468659045},{"fsize":185325,"hash":"FgbZ8ABgxYYO697oUG_3usT0emq7","key":"girl_b_img-de069d1c426c9c57cbf88efa49dc8e63.jpg","mimeType":"image/jpeg","putTime":14456632481781546},{"fsize":44312,"hash":"FvIXJnHlWXEkZ8zZmG_lW2h4oKwZ","key":"girl_b_img-de85316559a8215a6f51b5b774437bdd.jpg","mimeType":"image/jpeg","putTime":14456632485897408},{"fsize":145829,"hash":"Fgk_vO77bqNT-IyugwR9RroJxKxB","key":"girl_b_img-deaca738334d4413a81783edf81ae630.jpg","mimeType":"image/jpeg","putTime":14456632499080801},{"fsize":60043,"hash":"Fo0_YhPJOUUitD_PP_G7tH1Pjvrn","key":"girl_b_img-defa455645bd01c25a8a60be040b7dfb.jpg","mimeType":"image/jpeg","putTime":14456632503645181},{"fsize":70198,"hash":"Fk8YjqZLIyhXXZp4ZunDY0El-u5O","key":"girl_b_img-df504d02b6c176ea5eaa111edfca3574.jpg","mimeType":"image/jpeg","putTime":14456632510433488},{"fsize":3583820,"hash":"FrnsEIfFPoyYJpmcv13XxFvJRCwP","key":"girl_b_img-df01563da48978ef5e22013f0f457228.jpg","mimeType":"image/jpeg","putTime":14456632739187442},{"fsize":141403,"hash":"FqN7kGHQ4hiFMHaIBUa43qrrSy04","key":"girl_b_img-df3107420dfb2614afae6dbe6c9866bf.jpg","mimeType":"image/jpeg","putTime":14456632756075425},{"fsize":156208,"hash":"Fr8R0n1RYQEenxv8YiFB0a7jAdoZ","key":"girl_b_img-e02def485870d61f69c258a43fe02d6d.jpg","mimeType":"image/jpeg","putTime":14456632771221910},{"fsize":125780,"hash":"Fm7RAn3K8wzt2Ar5HCFIopxpfKOt","key":"girl_b_img-e03fc2598834c322578105eb9dcfd951.jpg","mimeType":"image/jpeg","putTime":14456632778584745},{"fsize":134652,"hash":"Fo2HxdutuT-PwundBc8JT1FB3VBo","key":"girl_b_img-e7fdd306f66d5b4d3823c0fbdd8b3dbc.jpg","mimeType":"image/jpeg","putTime":14456632785118056},{"fsize":30335,"hash":"Fp-bocrhtkjLzEiCfbU5RtDNGjBw","key":"girl_b_img-e9c582c799d01ea7568520c2155a66dd.jpg","mimeType":"image/jpeg","putTime":14456632788557281},{"fsize":93085,"hash":"FgMuiV0Z9TTrMnqJmXe-l2JKiwHV","key":"girl_b_img-e13f76e0e2e972907d9f21f2e3de94ad.jpg","mimeType":"image/jpeg","putTime":14456632795119273},{"fsize":64745,"hash":"Fm5MjlzLOj-ArU2lUs8XlyY0-feR","key":"girl_b_img-e23b1b3d3a6167230488e3d76e2565c4.jpg","mimeType":"image/jpeg","putTime":14456632798894931},{"fsize":138749,"hash":"FiJzI0bwGm9EEYmXUhaPChwZ4HVJ","key":"girl_b_img-e30b2d55c58f60b6390f793126956af5.jpg","mimeType":"image/jpeg","putTime":14456632806818682},{"fsize":85146,"hash":"FvwHW3-JiUtgdFg-xUvlETUl82Sm","key":"girl_b_img-e72fa81b1d5c3e7ff090f3caf97d0950.jpg","mimeType":"image/jpeg","putTime":14456632812864453},{"fsize":103414,"hash":"FqORkplKJclCKQxmlm9aYZffvjfB","key":"girl_b_img-e85f777a48b90396db3fcbc00d17d36b.jpg","mimeType":"image/jpeg","putTime":14456632827344502},{"fsize":67259,"hash":"FgMXYx-KOHibZl2yf_W541_fxUA3","key":"girl_b_img-e254e4172414d946585fca2df023df86.jpg","mimeType":"image/jpeg","putTime":14456632837173779},{"fsize":29696,"hash":"FtZ39vF52oVzJwhX5oBXqVtPzcdt","key":"girl_b_img-e695c6a40e28227831d1c2f84a82c9a0.jpg","mimeType":"image/jpeg","putTime":14456632841240436},{"fsize":1022458,"hash":"FvSfDml7lpIlP8Z3lMVtz0rwwJNW","key":"girl_b_img-e743e58bc4f813efb95649cff5a208db.gif","mimeType":"image/gif","putTime":14456632909651448},{"fsize":141546,"hash":"Fsr0Pg4hp_PS-OU3HhC3XOAboyco","key":"girl_b_img-e5005b32d0a1722d1f5447a632eaca94.jpg","mimeType":"image/jpeg","putTime":14456632916749036},{"fsize":482883,"hash":"FnP6MdeB2o4NX0kXZBzXeD1wKFnE","key":"girl_b_img-e5132bcbe104494904f839528e3a17c9.gif","mimeType":"image/gif","putTime":14456632975484685},{"fsize":93288,"hash":"FiTe3PkUZOr8TdZ-pfehmxQUNhJI","key":"girl_b_img-e47688dc3e778f391c2cf9f2367ac765.jpg","mimeType":"image/jpeg","putTime":14456632983762752},{"fsize":113360,"hash":"Frh4xd-s3FcFLrj0HnX5EGuPyTPc","key":"girl_b_img-e74756becd7f6fdf691bb2922ea32c26.jpg","mimeType":"image/jpeg","putTime":14456633004466167},{"fsize":130912,"hash":"FmWNV82OS_MohCjib4aqe-LCQK3v","key":"girl_b_img-e7794207f60f861aafe4221f5e5ff24e.jpg","mimeType":"image/jpeg","putTime":14456633017965909},{"fsize":108135,"hash":"Fjb2_YBzeLCsoxYOzN00SiSTVx1b","key":"girl_b_img-e2379049309de251be66ddbe4803f579.jpg","mimeType":"image/jpeg","putTime":14456633028876590},{"fsize":52211,"hash":"FlcIDu90kmfXm4Y3uHZVMw51scMt","key":"girl_b_img-e94758788909577228209f9be5efe500.jpg","mimeType":"image/jpeg","putTime":14456633039469766},{"fsize":60059,"hash":"FhUP2nMjA0c4SLvFjovdx4_R9sCo","key":"girl_b_img-ea8244697065b159a6a7f519d5b7fbec.jpg","mimeType":"image/jpeg","putTime":14456633050628733},{"fsize":51201,"hash":"FooWu6Pp-aWfRwikbnKipdYLS7cI","key":"girl_b_img-eb042b76ee4f47c16e5f06003ff48d49.jpg","mimeType":"image/jpeg","putTime":14456633059898384},{"fsize":230499,"hash":"FnrAOQY6oRrGYKy9zZ7l17S2-Qd1","key":"girl_b_img-ebe9f4df044cd0dd6f6b6fe9ff0e8e18.jpg","mimeType":"image/jpeg","putTime":14456633077841811},{"fsize":15474,"hash":"Fs3wzDcBjdNVgkP2XxgXHOeFkZYA","key":"girl_b_img-ecbff0a6483dba46388e16e919b54985.jpg","mimeType":"image/jpeg","putTime":14456633079681085},{"fsize":98618,"hash":"FqaPTmP7ZA2sllzZIY_k2HRQRHp6","key":"girl_b_img-ecedf4e81f728a1c2abd3dc2e4022d2b.jpg","mimeType":"image/jpeg","putTime":14456633100255573},{"fsize":223210,"hash":"FknHge8_xlF60k51vnVQifHsnLFO","key":"girl_b_img-ed814fec381f5020d2bc446822088939.jpg","mimeType":"image/jpeg","putTime":14456633116672016},{"fsize":137247,"hash":"FjfIGMcCgDDWTAX0OJJ89oH65frI","key":"girl_b_img-edaca3a7fef2bd7e817532429abc33fe.jpg","mimeType":"image/jpeg","putTime":14456633129211972},{"fsize":46083,"hash":"Fud1jbGuHQCmJLrv-NsEgW7Z62aJ","key":"girl_b_img-edb7c35fc397dd86eec39df3c2e19064.jpg","mimeType":"image/jpeg","putTime":14456633133118741},{"fsize":40305,"hash":"FswDVqZsOR7jq0yiTJl86173vsZO","key":"girl_b_img-ee4a8f775c424f933e9050bcdbc31333.jpg","mimeType":"image/jpeg","putTime":14456633136593723},{"fsize":143352,"hash":"FhnBtC8rBdUx7ZDcZ-UjHELiwDrf","key":"girl_b_img-ee22d4be4a6ff3792e71b9e5104cb2b2.jpg","mimeType":"image/jpeg","putTime":14456633150515367},{"fsize":99086,"hash":"FtZjneheu0Fz74fJyNn8o0425krE","key":"girl_b_img-ef2bb2d296d661dd65740dc652c42865.jpg","mimeType":"image/jpeg","putTime":14456633167567579},{"fsize":2595578,"hash":"Fmg2PjbRUUSBQmPRuwJnvI9McCDs","key":"girl_b_img-efddf317966fcb84e4a45c8a3f4c59b9.jpg","mimeType":"image/jpeg","putTime":14456633412849760},{"fsize":162119,"hash":"Fiu1jALX6-tBYnysL53651jd8KD8","key":"girl_b_img-f0b7b69f742bb7706869b04fd8289fa7.jpg","mimeType":"image/jpeg","putTime":14456633423401905},{"fsize":2059567,"hash":"FsA3fn7LHCI_NqiomqQGWL-pK4pI","key":"girl_b_img-f0de809b2acf5cb6a25694030c395fd1.jpg","mimeType":"image/jpeg","putTime":14456633545012723},{"fsize":312036,"hash":"FpX_Yo8ERcUd96ZEJEqpnsTpojnJ","key":"girl_b_img-f1fc66962741e3e07c381850092456b5.jpg","mimeType":"image/jpeg","putTime":14456633560564543},{"fsize":363541,"hash":"FqqZAPEkSFBj2NesA6EipEEhoEHy","key":"girl_b_img-f02dd2c2c5d07d70e2e809a689c4db92.jpg","mimeType":"image/jpeg","putTime":14456633583112606},{"fsize":157920,"hash":"FkwNPKDMfmxVX_EiEwK_1vy84NvE","key":"girl_b_img-f3bfb75614809f7f6b27a6c0bc75f301.jpg","mimeType":"image/jpeg","putTime":14456633598769847},{"fsize":93512,"hash":"FhpJQYx1UrWlRk0iHED4jbKhPBHG","key":"girl_b_img-f4a929d78ea51eab06d2703acd2234ec.jpg","mimeType":"image/jpeg","putTime":14456633614442828},{"fsize":161144,"hash":"FpaQIV75yfrxq0lzq6nvVxsR6j2k","key":"girl_b_img-f4c2e3493a088d2bdbcb34ffbd761960.jpg","mimeType":"image/jpeg","putTime":14456633627554001},{"fsize":109253,"hash":"FjVQL0pPXdKH4fqu6aKGnVqU1pGZ","key":"girl_b_img-f6d83ee52f5bd674695add7180519f40.jpg","mimeType":"image/jpeg","putTime":14456633651192339},{"fsize":69460,"hash":"FiYeauiPrBe5qlDyd6-wJi_9-JJD","key":"girl_b_img-f6ebf1201200810ded3b18864e11e0fe.jpg","mimeType":"image/jpeg","putTime":14456633668155288},{"fsize":4608346,"hash":"lsg7sYLKv1ZdevGQyIaW2xDoRg-i","key":"girl_b_img-f8a46c120dbf5f8b8d936b73c3480f67.gif","mimeType":"image/gif","putTime":14456634029056086},{"fsize":209013,"hash":"Fq-MYo9nVz_P4kR0nMgUuzb9hC-b","key":"girl_b_img-f36a2235f3a81b7bfbd47ec0104b6c05.jpg","mimeType":"image/jpeg","putTime":14456634047117383},{"fsize":88794,"hash":"FksgHX8mxuvvxcBviZMxOqikoPsr","key":"girl_b_img-f58b2350e5ec8632391274cbd029ba68.jpg","mimeType":"image/jpeg","putTime":14456634062826390},{"fsize":97544,"hash":"FnOttB73h5EJeDidM3YL_kKDX4iO","key":"girl_b_img-f78ad6e0461fecfbf19c0f8ff24bc318.jpg","mimeType":"image/jpeg","putTime":14456634074516371},{"fsize":175159,"hash":"FkLKgzV-DDGGS5FTzMDZycV11cal","key":"girl_b_img-f904e169bad6666aaa28fe1bb5f7b501.jpg","mimeType":"image/jpeg","putTime":14456634091817198},{"fsize":47040,"hash":"FhoRNoT4lX6K61ROBX9BKzY49R1c","key":"girl_b_img-f4049f941945614d438f5701bee39eea.jpg","mimeType":"image/jpeg","putTime":14456634097721438},{"fsize":3093383,"hash":"Ft3TF5f_-TNxlEo5LSI6Y1ibar41","key":"girl_b_img-f8141cb08de94f5dac7dc3d990d5fb7f.jpg","mimeType":"image/jpeg","putTime":14456634423775887},{"fsize":96489,"hash":"FvnXv9TAM4VwIoHl9WIFLf7ZOKzn","key":"girl_b_img-f13259b0241cde180f513d20f586b0be.jpg","mimeType":"image/jpeg","putTime":14456634430958714},{"fsize":163799,"hash":"FvZGfhU1gBIgCTrpmuR27bfW5xCM","key":"girl_b_img-f737759aae1d41ae4fb968997be7484b.jpg","mimeType":"image/jpeg","putTime":14456634444456717},{"fsize":723631,"hash":"FnYYs_CJ9RHytPOgQWlf1FHF0u2Q","key":"girl_b_img-f805444ae94a0ebfe9e39f9472bf6a91.jpg","mimeType":"image/jpeg","putTime":14456634517454309},{"fsize":65592,"hash":"Fja-jC6ImIR470I5GJVL3RTpgGiA","key":"girl_b_img-fa5aa9d96f6d4645d38276e63a5f091b.jpg","mimeType":"image/jpeg","putTime":14456634545653964},{"fsize":599989,"hash":"FrJSKJA7Ky-DrQSgTNs3GwtJAz3C","key":"girl_b_img-fba082487a23b1906bd879e2bc0b5144.jpg","mimeType":"image/jpeg","putTime":14456634621370721},{"fsize":561421,"hash":"FpRIp520VXWvA6a5AlOaRW02rL2h","key":"girl_b_img-fbf3ca5a249a0efcee7e9215b61afd4c.jpg","mimeType":"image/jpeg","putTime":14456634686292441},{"fsize":69837,"hash":"FjhnFC-LAYWx7liHpmopzJ3_pJO7","key":"girl_b_img-fdbabc807c0bea9090a94f564e836fe7.jpg","mimeType":"image/jpeg","putTime":14456634691343874},{"fsize":88400,"hash":"FlMv25yKM54pGoCPSYrJbIy7l_lO","key":"girl_b_img-fe59140f9f94c59f100764674d487ebb.jpg","mimeType":"image/jpeg","putTime":14456634696639051},{"fsize":91748,"hash":"FgLwgVImPnyTMoeYuge9DDnn-80j","key":"girl_b_img-fef1f50c65d7187d05f9a041637d8400.jpg","mimeType":"image/jpeg","putTime":14456634701533293},{"fsize":2792656,"hash":"Fg60yv1u0PKssO8YmPiI1YhX3QFa","key":"girl_b_img-ff2a76d4e872c4f5e88322cf4504cbb1.gif","mimeType":"image/gif","putTime":14456635016644540},{"fsize":114367,"hash":"Ft2Afr_XCk1BJqhLaEOdaAM7V8gL","key":"girl_b_img-ff772ab9ff1567718f81d3af7e1bc84b.jpg","mimeType":"image/jpeg","putTime":14456635028276357},{"fsize":376367,"hash":"Fo0Sx4Vs9NANNU2KNSTJkkqnl6np","key":"girl_b_img-ffd86bcf90ccaf93f0c5257c41f1faa7.jpg","mimeType":"image/jpeg","putTime":14456635048529422},{"fsize":65867,"hash":"Fq-az3cZsP1oIN9Q9U6G0v49PqJC","key":"girl_b_img-ffff0aae3a641c2616c54c307cb43ee6.jpg","mimeType":"image/jpeg","putTime":14456635065425847},{"fsize":3944,"hash":"Fl2Th3WZ9HhfRH7sB8Yzn_inmcbY","key":"swagger.json","mimeType":"application/json","putTime":14515761756427960},{"fsize":330402,"hash":"FlRQjXmF-p6aef3oHDI10l7EZsVf","key":"122eqwqwqw.jpg","mimeType":"image/jpeg","putTime":14616967528828267},{"fsize":76261,"hash":"FiP-TPwKv_9ZfGIcMI3WoyYTnsKH","key":"ghdgergqweq.jpg","mimeType":"image/jpeg","putTime":14616968132891962},{"fsize":73759,"hash":"FrrOIfHeShvslsXpbdj_qFH_wPsR","key":"20160612132341833.jpg790x600.jpg","mimeType":"image/jpeg","putTime":14730044955741659},{"fsize":611215,"hash":"Fn6Krr0JH_f7fVBUmtZ5m03aO3Ck","key":"2bcdc656-109b-4cb2-aba3-0e128883938b.jpg","mimeType":"image/jpeg","putTime":14730045097537778},{"fsize":204735,"hash":"Ft0y1Vigje2eNK7U9peMJupgPCnV","key":"keykeykeyddd","mimeType":"image/jpeg;charset=UTF-8","putTime":14842900647539082}]